[{"c":"3481","n":"群創","p":"66.00","cg":"1.6000","v":"954222795"},{"c":"2344","n":"華邦電","p":"222.00","cg":"3.5000","v":"403194761"},{"c":"00403A","n":"主動統一升級50","p":"11.38","cg":"0.3500","v":"400006178"},{"c":"6116","n":"彩晶","p":"19.95","cg":"1.1500","v":"316411406"},{"c":"2409","n":"友達","p":"30.95","cg":"2.8000","v":"297702512"},{"c":"00631L","n":"元大台灣50正2","p":"41.32","cg":"2.9900","v":"290716085"},{"c":"00632R","n":"元大台灣50反1","p":"9.65","cg":"-0.3800","v":"273674962"},{"c":"00981A","n":"主動統一台股增長","p":"32.23","cg":"0.7300","v":"267931647"},{"c":"00405A","n":"主動富邦台灣龍耀","p":"9.79","cg":"0.1500","v":"190248610"},{"c":"1802","n":"台玻","p":"76.60","cg":"5.3000","v":"172733646"},{"c":"009816","n":"凱基台灣TOP50","p":"16.17","cg":"0.4900","v":"162560447"},{"c":"00919","n":"群益台灣精選高息","p":"30.80","cg":"-0.0100","v":"157725986"},{"c":"00991A","n":"主動復華未來50","p":"21.33","cg":"0.6500","v":"140946220"},{"c":"2337","n":"旺宏","p":"185.50","cg":"16.5000","v":"136155871"},{"c":"6770","n":"力積電","p":"81.60","cg":"7.4000","v":"133236652"},{"c":"2002","n":"中鋼","p":"19.50","cg":"0.4000","v":"129639571"},{"c":"0050","n":"元大台灣50","p":"111.15","cg":"3.8500","v":"116042256"},{"c":"2884","n":"玉山金","p":"35.80","cg":"0.4000","v":"106058238"},{"c":"00988A","n":"主動統一全球創新","p":"23.73","cg":"0.7700","v":"104088751"},{"c":"009821","n":"野村稀土關鍵資源","p":"17.21","cg":"1.6500","v":"98536665"},{"c":"2408","n":"南亞科","p":"505.00","cg":"45.5000","v":"96419516"},{"c":"2890","n":"永豐金","p":"39.80","cg":"0.0000","v":"93780276"},{"c":"00918","n":"大華優利高填息30","p":"32.11","cg":"0.1100","v":"92837027"},{"c":"2324","n":"仁寶","p":"37.50","cg":"-0.2500","v":"92199498"},{"c":"1605","n":"華新","p":"40.75","cg":"1.7500","v":"91792161"},{"c":"2883","n":"凱基金","p":"30.35","cg":"-0.4000","v":"85250985"},{"c":"2449","n":"京元電子","p":"339.00","cg":"30.5000","v":"81551317"},{"c":"9105","n":"泰金寶-DR","p":"9.70","cg":"0.1700","v":"77199818"},{"c":"00400A","n":"主動國泰動能高息","p":"15.57","cg":"0.4500","v":"73628153"},{"c":"1905","n":"華紙","p":"18.45","cg":"1.3500","v":"73132002"},{"c":"2317","n":"鴻海","p":"268.50","cg":"0.0000","v":"67145972"},{"c":"2303","n":"聯電","p":"160.00","cg":"14.5000","v":"66171376"},{"c":"2356","n":"英業達","p":"67.80","cg":"0.1000","v":"63430817"},{"c":"00992A","n":"主動群益科技創新","p":"19.42","cg":"0.4400","v":"62720250"},{"c":"2332","n":"友訊","p":"18.95","cg":"-1.1000","v":"62717537"},{"c":"6239","n":"力成","p":"366.00","cg":"2.5000","v":"62661099"},{"c":"2489","n":"瑞軒","p":"50.70","cg":"2.5500","v":"62617576"},{"c":"2327","n":"國巨*","p":"1065.00","cg":"-15.0000","v":"62351693"},{"c":"2887","n":"台新新光金","p":"32.05","cg":"-0.4000","v":"62139229"},{"c":"2610","n":"華航","p":"21.80","cg":"-0.2000","v":"56950265"},{"c":"6282","n":"康舒","p":"63.90","cg":"5.8000","v":"56918124"},{"c":"1303","n":"南亞","p":"152.50","cg":"13.5000","v":"56846553"},{"c":"2618","n":"長榮航","p":"41.65","cg":"-0.9000","v":"54152128"},{"c":"2886","n":"兆豐金","p":"44.75","cg":"-0.7500","v":"53658490"},{"c":"2891","n":"中信金","p":"70.50","cg":"-1.4000","v":"52760387"},{"c":"1301","n":"台塑","p":"52.40","cg":"0.7000","v":"51915785"},{"c":"8150","n":"南茂","p":"114.00","cg":"10.0000","v":"51900604"},{"c":"2834","n":"臺企銀","p":"17.45","cg":"-0.0500","v":"50720734"},{"c":"2369","n":"菱生","p":"40.50","cg":"3.6500","v":"50186512"},{"c":"00664R","n":"國泰臺灣加權反1","p":"1.56","cg":"-0.0600","v":"49579047"},{"c":"00878","n":"國泰永續高股息","p":"34.12","cg":"0.4500","v":"48412504"},{"c":"0056","n":"元大高股息","p":"54.05","cg":"1.2500","v":"47649273"},{"c":"1314","n":"中石化","p":"8.04","cg":"0.2600","v":"47178387"},{"c":"2892","n":"第一金","p":"32.30","cg":"-0.3000","v":"46847145"},{"c":"0052","n":"富邦科技","p":"65.25","cg":"2.4500","v":"46591322"},{"c":"3042","n":"晶技","p":"198.00","cg":"-18.0000","v":"46094673"},{"c":"3231","n":"緯創","p":"162.50","cg":"1.0000","v":"45905638"},{"c":"2301","n":"光寶科","p":"231.50","cg":"21.0000","v":"45443527"},{"c":"2330","n":"台積電","p":"2510.00","cg":"100.0000","v":"45207883"},{"c":"00990A","n":"主動元大AI新經濟","p":"21.73","cg":"0.7600","v":"44980903"},{"c":"2880","n":"華南金","p":"37.60","cg":"-0.7500","v":"43716046"},{"c":"00665L","n":"富邦恒生國企正2","p":"8.32","cg":"-0.0800","v":"43589869"},{"c":"4904","n":"遠傳","p":"108.00","cg":"-0.5000","v":"43158866"},{"c":"1101","n":"台泥","p":"24.35","cg":"-0.1500","v":"40462324"},{"c":"00712","n":"復華富時不動產","p":"8.57","cg":"-0.0300","v":"39183720"},{"c":"3715","n":"定穎投控","p":"194.50","cg":"15.5000","v":"38842852"},{"c":"00402A","n":"主動安聯美國科技","p":"10.03","cg":"0.0800","v":"38711457"},{"c":"2353","n":"宏碁","p":"34.00","cg":"-0.4000","v":"38386913"},{"c":"8112","n":"至上","p":"100.50","cg":"2.3000","v":"38207426"},{"c":"00999A","n":"主動野村臺灣高息","p":"11.43","cg":"0.1200","v":"38073807"},{"c":"2609","n":"陽明","p":"52.30","cg":"1.0000","v":"38001527"},{"c":"2885","n":"元大金","p":"68.80","cg":"0.8000","v":"37678724"},{"c":"2426","n":"鼎元","p":"89.90","cg":"8.1000","v":"37157368"},{"c":"3711","n":"日月光投控","p":"674.00","cg":"61.0000","v":"37123135"},{"c":"1409","n":"新纖","p":"28.15","cg":"2.5500","v":"36341896"},{"c":"6213","n":"聯茂","p":"308.00","cg":"28.0000","v":"36208426"},{"c":"00929","n":"復華台灣科技優息","p":"32.16","cg":"1.0600","v":"35743009"},{"c":"2342","n":"茂矽","p":"58.60","cg":"3.4000","v":"35417003"},{"c":"2882","n":"國泰金","p":"113.00","cg":"-2.5000","v":"34442840"},{"c":"4958","n":"臻鼎-KY","p":"622.00","cg":"-20.0000","v":"34319805"},{"c":"2312","n":"金寶","p":"35.85","cg":"0.3500","v":"34183663"},{"c":"2375","n":"凱美","p":"219.00","cg":"0.0000","v":"33433511"},{"c":"1326","n":"台化","p":"56.20","cg":"2.0000","v":"33297275"},{"c":"00637L","n":"元大滬深300正2","p":"22.64","cg":"0.5700","v":"32972368"},{"c":"2845","n":"遠東銀","p":"12.85","cg":"-0.1000","v":"32725246"},{"c":"1402","n":"遠東新","p":"28.80","cg":"-0.0500","v":"32428444"},{"c":"00406A","n":"主動中信台灣收益","p":"10.60","cg":"0.3100","v":"32107362"},{"c":"00953B","n":"群益優選非投等債","p":"9.63","cg":"0.0200","v":"31503388"},{"c":"3673","n":"TPK-KY","p":"88.50","cg":"2.3000","v":"30691658"},{"c":"6153","n":"嘉聯益","p":"23.95","cg":"-0.5000","v":"30661452"},{"c":"8110","n":"華東","p":"62.60","cg":"3.4000","v":"30250325"},{"c":"2401","n":"凌陽","p":"34.00","cg":"1.7500","v":"30210673"},{"c":"3714","n":"富采","p":"72.90","cg":"5.7000","v":"29547756"},{"c":"2313","n":"華通","p":"259.50","cg":"0.0000","v":"29090333"},{"c":"00982A","n":"主動群益台灣強棒","p":"25.45","cg":"0.6200","v":"28078135"},{"c":"2484","n":"希華","p":"66.90","cg":"-4.3000","v":"27790961"},{"c":"3037","n":"欣興","p":"1005.00","cg":"37.0000","v":"27784024"},{"c":"6271","n":"同欣電","p":"266.50","cg":"24.0000","v":"27332596"},{"c":"00940","n":"元大台灣價值高息","p":"12.83","cg":"0.1300","v":"27204830"},{"c":"3090","n":"日電貿","p":"335.50","cg":"3.0000","v":"27078260"},{"c":"2498","n":"宏達電","p":"50.40","cg":"0.0000","v":"26835183"},{"c":"1714","n":"和桐","p":"18.35","cg":"-2.0000","v":"26230232"},{"c":"009820","n":"元大納斯達克精選","p":"10.18","cg":"0.0600","v":"25109639"},{"c":"6257","n":"矽格","p":"242.50","cg":"7.5000","v":"25036209"},{"c":"2542","n":"興富發","p":"42.70","cg":"-2.0500","v":"24903981"},{"c":"8105","n":"凌巨","p":"22.90","cg":"1.0000","v":"24766765"},{"c":"00673R","n":"期元大S&P原油反1","p":"14.76","cg":"-0.2300","v":"24602345"},{"c":"2881","n":"富邦金","p":"138.50","cg":"0.5000","v":"24444307"},{"c":"00997A","n":"主動群益美國增長","p":"14.74","cg":"0.3100","v":"24196214"},{"c":"00927","n":"群益半導體收益","p":"43.53","cg":"2.2800","v":"24183929"},{"c":"5876","n":"上海商銀","p":"41.45","cg":"-1.0500","v":"23506048"},{"c":"00680L","n":"元大美債20正2","p":"7.05","cg":"-0.0600","v":"23400300"},{"c":"2464","n":"盟立","p":"173.00","cg":"1.0000","v":"23281729"},{"c":"5880","n":"合庫金","p":"24.45","cg":"-0.3000","v":"23219136"},{"c":"4906","n":"正文","p":"47.65","cg":"0.0000","v":"23143645"},{"c":"2388","n":"威盛","p":"84.40","cg":"0.0000","v":"23091050"},{"c":"00753L","n":"中信中國50正2","p":"8.92","cg":"-0.0100","v":"22752058"},{"c":"9904","n":"寶成","p":"26.10","cg":"-0.0500","v":"22724237"},{"c":"1711","n":"永光","p":"49.55","cg":"4.2500","v":"22663600"},{"c":"4938","n":"和碩","p":"82.00","cg":"-0.9000","v":"22605594"},{"c":"1312","n":"國喬","p":"14.00","cg":"0.5000","v":"22473896"},{"c":"2340","n":"台亞","p":"42.80","cg":"2.8500","v":"22297392"},{"c":"2441","n":"超豐","p":"140.00","cg":"5.0000","v":"22168250"},{"c":"6209","n":"今國光","p":"97.20","cg":"0.1000","v":"21879361"},{"c":"2867","n":"三商壽","p":"8.69","cg":"-0.0500","v":"21713316"},{"c":"3060","n":"銘異","p":"41.65","cg":"3.7500","v":"21692248"},{"c":"8046","n":"南電","p":"864.00","cg":"-10.0000","v":"21056848"},{"c":"3706","n":"神達","p":"87.40","cg":"0.5000","v":"20974685"},{"c":"2801","n":"彰銀","p":"22.85","cg":"0.0000","v":"20842731"},{"c":"6155","n":"鈞寶","p":"96.70","cg":"-1.8000","v":"20715575"},{"c":"3189","n":"景碩","p":"796.00","cg":"72.0000","v":"20663905"},{"c":"2367","n":"燿華","p":"60.60","cg":"-0.7000","v":"20655295"},{"c":"1708","n":"東鹼","p":"51.60","cg":"1.3000","v":"20614338"},{"c":"00984D","n":"主動聯博全球非投","p":"10.11","cg":"0.0000","v":"20571717"},{"c":"00404A","n":"主動聯博動能50","p":"10.52","cg":"0.3400","v":"20566125"},{"c":"2492","n":"華新科","p":"617.00","cg":"56.0000","v":"20258065"},{"c":"00891","n":"中信關鍵半導體","p":"39.11","cg":"1.7700","v":"20093591"},{"c":"3550","n":"聯穎","p":"35.90","cg":"-1.3500","v":"20071272"},{"c":"1319","n":"東陽","p":"84.80","cg":"0.0000","v":"20044867"},{"c":"2105","n":"正新","p":"30.05","cg":"0.4000","v":"20028178"},{"c":"2382","n":"廣達","p":"380.00","cg":"4.0000","v":"20023542"},{"c":"1102","n":"亞泥","p":"36.35","cg":"0.5500","v":"19843503"},{"c":"2323","n":"中環","p":"11.90","cg":"0.1500","v":"19450954"},{"c":"1310","n":"台苯","p":"10.15","cg":"0.8900","v":"19401898"},{"c":"2634","n":"漢翔","p":"50.10","cg":"2.9000","v":"19052628"},{"c":"2633","n":"台灣高鐵","p":"25.95","cg":"-0.2000","v":"18555998"},{"c":"3576","n":"聯合再生","p":"18.05","cg":"0.0500","v":"18162526"},{"c":"6168","n":"宏齊","p":"31.10","cg":"2.8000","v":"18103075"},{"c":"2457","n":"飛宏","p":"31.50","cg":"2.7000","v":"17959829"},{"c":"2486","n":"一詮","p":"272.00","cg":"-4.5000","v":"17859431"},{"c":"6919","n":"康霈*","p":"119.50","cg":"10.5000","v":"17823430"},{"c":"1504","n":"東元","p":"72.20","cg":"2.2000","v":"17785287"},{"c":"3450","n":"聯鈞","p":"557.00","cg":"-8.0000","v":"17551853"},{"c":"1727","n":"中華化","p":"102.00","cg":"7.9000","v":"17509011"},{"c":"2855","n":"統一證","p":"52.00","cg":"-0.2000","v":"17358078"},{"c":"1513","n":"中興電","p":"181.00","cg":"4.5000","v":"17056003"},{"c":"3006","n":"晶豪科","p":"254.00","cg":"16.5000","v":"16999688"},{"c":"6005","n":"群益證","p":"39.80","cg":"0.1500","v":"16939884"},{"c":"2308","n":"台達電","p":"2150.00","cg":"0.0000","v":"16874717"},{"c":"6415","n":"矽力*-KY","p":"673.00","cg":"44.0000","v":"16848835"},{"c":"6269","n":"台郡","p":"87.50","cg":"7.9000","v":"16775499"},{"c":"00882","n":"中信中國高股息","p":"15.55","cg":"0.0300","v":"16587515"},{"c":"00994A","n":"主動第一金台股優","p":"18.52","cg":"0.4500","v":"16497798"},{"c":"1809","n":"中釉","p":"56.50","cg":"5.1000","v":"16413912"},{"c":"2399","n":"映泰","p":"51.60","cg":"3.5500","v":"16358972"},{"c":"2305","n":"全友","p":"37.00","cg":"3.3500","v":"16289442"},{"c":"3035","n":"智原","p":"229.50","cg":"20.5000","v":"16276996"},{"c":"2603","n":"長榮","p":"193.00","cg":"0.0000","v":"16263171"},{"c":"2371","n":"大同","p":"28.15","cg":"-0.1500","v":"15967517"},{"c":"3036","n":"文曄","p":"225.00","cg":"2.5000","v":"15949474"},{"c":"2472","n":"立隆電","p":"393.50","cg":"-8.5000","v":"15931682"},{"c":"00688L","n":"國泰20年美債正2","p":"7.03","cg":"-0.0600","v":"15543323"},{"c":"1717","n":"長興","p":"74.70","cg":"2.3000","v":"15232163"},{"c":"00686R","n":"群益臺灣加權反1","p":"0.95","cg":"-0.0500","v":"15135335"},{"c":"00947","n":"台新臺灣IC設計","p":"43.02","cg":"1.7200","v":"15127881"},{"c":"2363","n":"矽統","p":"69.10","cg":"6.2000","v":"14903173"},{"c":"6285","n":"啟碁","p":"268.00","cg":"-6.0000","v":"14879954"},{"c":"1216","n":"統一","p":"74.30","cg":"-0.2000","v":"14851130"},{"c":"2027","n":"大成鋼","p":"41.10","cg":"0.1000","v":"14737337"},{"c":"2302","n":"麗正","p":"47.65","cg":"0.6500","v":"14703447"},{"c":"2812","n":"台中銀","p":"19.65","cg":"-0.1500","v":"14702604"},{"c":"8131","n":"福懋科","p":"78.80","cg":"2.9000","v":"14698073"},{"c":"4526","n":"東台","p":"43.05","cg":"3.9000","v":"14580133"},{"c":"009819","n":"中信數據及電力","p":"10.64","cg":"0.1500","v":"14345164"},{"c":"00676R","n":"富邦臺灣加權反1","p":"5.32","cg":"-0.2100","v":"14135531"},{"c":"00715L","n":"期街口布蘭特正2","p":"38.49","cg":"1.1400","v":"14103485"},{"c":"2515","n":"中工","p":"13.55","cg":"0.2000","v":"13906752"},{"c":"3312","n":"弘憶股","p":"67.40","cg":"4.6000","v":"13840745"},{"c":"1718","n":"中纖","p":"9.78","cg":"-0.0800","v":"13806893"},{"c":"00663L","n":"國泰臺灣加權正2","p":"120.20","cg":"8.3000","v":"13734806"},{"c":"6191","n":"精成科","p":"103.50","cg":"3.0000","v":"13733547"},{"c":"009805","n":"新光美國電力基建","p":"16.91","cg":"0.2400","v":"13550197"},{"c":"5469","n":"瀚宇博","p":"90.60","cg":"3.8000","v":"13541172"},{"c":"1514","n":"亞力","p":"127.00","cg":"5.5000","v":"13514257"},{"c":"8422","n":"可寧衛*","p":"28.95","cg":"0.8500","v":"13420080"},{"c":"3033","n":"威健","p":"51.20","cg":"1.7000","v":"13382386"},{"c":"6176","n":"瑞儀","p":"90.20","cg":"2.3000","v":"13235707"},{"c":"2406","n":"國碩","p":"35.60","cg":"0.7500","v":"13191495"},{"c":"2377","n":"微星","p":"137.00","cg":"-1.5000","v":"13017671"},{"c":"5871","n":"中租-KY","p":"118.00","cg":"4.0000","v":"13013815"},{"c":"2376","n":"技嘉","p":"339.50","cg":"-4.5000","v":"13004047"},{"c":"2436","n":"偉詮電","p":"78.60","cg":"5.2000","v":"12905162"},{"c":"2329","n":"華泰","p":"58.50","cg":"2.9000","v":"12710395"},{"c":"9945","n":"潤泰新","p":"26.80","cg":"-0.7000","v":"12340064"},{"c":"2402","n":"毅嘉","p":"71.30","cg":"1.3000","v":"11933100"},{"c":"2458","n":"義隆","p":"178.50","cg":"6.5000","v":"11709619"},{"c":"2454","n":"聯發科","p":"4465.00","cg":"75.0000","v":"11596124"},{"c":"00935","n":"野村臺灣新科技50","p":"64.20","cg":"1.9500","v":"11542193"},{"c":"8028","n":"昇陽半導體","p":"322.50","cg":"11.0000","v":"11432116"},{"c":"00980A","n":"主動野村臺灣優選","p":"25.71","cg":"0.6600","v":"11320460"},{"c":"00896","n":"中信綠能及電動車","p":"28.55","cg":"0.5800","v":"11305958"},{"c":"00881","n":"國泰台灣科技龍頭","p":"57.35","cg":"1.9500","v":"11287692"},{"c":"3045","n":"台灣大","p":"118.50","cg":"-0.5000","v":"11199373"},{"c":"3034","n":"聯詠","p":"567.00","cg":"51.0000","v":"11170070"},{"c":"4989","n":"榮科","p":"94.00","cg":"8.5000","v":"11160142"},{"c":"00993A","n":"主動安聯台灣","p":"14.64","cg":"0.3500","v":"11119341"},{"c":"00650L","n":"復華香港正2","p":"15.04","cg":"-0.0200","v":"11051849"},{"c":"8039","n":"台虹","p":"153.00","cg":"7.5000","v":"10796789"},{"c":"00922","n":"國泰台灣領袖50","p":"42.64","cg":"1.4200","v":"10792006"},{"c":"2485","n":"兆赫","p":"60.60","cg":"-1.1000","v":"10636712"},{"c":"6443","n":"元晶","p":"39.00","cg":"-0.3500","v":"10554940"},{"c":"4927","n":"泰鼎-KY","p":"52.10","cg":"1.0000","v":"10371130"},{"c":"2101","n":"南港","p":"32.05","cg":"-0.4000","v":"10223595"},{"c":"3094","n":"聯傑","p":"41.80","cg":"0.0000","v":"10181025"},{"c":"4916","n":"事欣科","p":"105.00","cg":"1.5000","v":"10090947"},{"c":"5285","n":"界霖","p":"102.50","cg":"8.8000","v":"10076078"},{"c":"2354","n":"鴻準","p":"58.00","cg":"0.1000","v":"10039698"},{"c":"4919","n":"新唐","p":"216.00","cg":"19.5000","v":"10024799"},{"c":"3019","n":"亞光","p":"163.00","cg":"2.5000","v":"10008263"},{"c":"1313","n":"聯成","p":"12.05","cg":"0.0000","v":"9962850"},{"c":"5471","n":"松翰","p":"63.60","cg":"2.7000","v":"9863302"},{"c":"8070","n":"長華*","p":"56.90","cg":"1.9000","v":"9810340"},{"c":"6962","n":"奕力-KY","p":"40.05","cg":"1.1500","v":"9748938"},{"c":"6834","n":"天二科技","p":"111.50","cg":"10.0000","v":"9672970"},{"c":"2501","n":"國建","p":"24.85","cg":"-2.0000","v":"9637556"},{"c":"9907","n":"統一實","p":"15.50","cg":"0.0000","v":"9624359"},{"c":"6742","n":"澤米","p":"69.00","cg":"0.0000","v":"9338236"},{"c":"8033","n":"雷虎","p":"142.00","cg":"12.5000","v":"9323958"},{"c":"009802","n":"富邦旗艦50","p":"20.16","cg":"0.2700","v":"9290150"},{"c":"00900","n":"富邦特選高股息30","p":"19.85","cg":"0.2700","v":"9192882"},{"c":"2355","n":"敬鵬","p":"58.70","cg":"0.8000","v":"9160422"},{"c":"6525","n":"捷敏-KY","p":"155.00","cg":"12.0000","v":"9125433"},{"c":"8104","n":"錸寶","p":"42.30","cg":"-0.0500","v":"9007312"},{"c":"3016","n":"嘉晶","p":"139.00","cg":"12.5000","v":"8906871"},{"c":"00985B","n":"群益ESG投等債0-5","p":"10.19","cg":"0.0100","v":"8899569"},{"c":"2352","n":"佳世達","p":"31.45","cg":"0.6000","v":"8875914"},{"c":"00961","n":"FT臺灣永續高息","p":"12.88","cg":"-0.0300","v":"8787396"},{"c":"2014","n":"中鴻","p":"17.80","cg":"0.1000","v":"8719369"},{"c":"6719","n":"力智","p":"286.00","cg":"25.5000","v":"8709729"},{"c":"4976","n":"佳凌","p":"40.95","cg":"-2.9500","v":"8698786"},{"c":"00984A","n":"主動安聯台灣高息","p":"17.32","cg":"0.3900","v":"8670923"},{"c":"00713","n":"元大台灣高息低波","p":"60.80","cg":"0.0000","v":"8653345"},{"c":"3049","n":"精金","p":"14.30","cg":"-0.1500","v":"8643605"},{"c":"00996A","n":"主動兆豐台灣豐收","p":"16.32","cg":"0.2600","v":"8575041"},{"c":"3702","n":"大聯大","p":"112.50","cg":"0.5000","v":"8555913"},{"c":"3048","n":"益登","p":"72.40","cg":"-1.1000","v":"8478065"},{"c":"2351","n":"順德","p":"214.50","cg":"19.5000","v":"8471649"},{"c":"6672","n":"騰輝電子-KY","p":"255.50","cg":"10.0000","v":"8440456"},{"c":"00946","n":"群益科技高息成長","p":"15.85","cg":"0.4500","v":"8434685"},{"c":"1304","n":"台聚","p":"13.70","cg":"0.1500","v":"8383029"},{"c":"2412","n":"中華電","p":"144.50","cg":"0.5000","v":"8346517"},{"c":"4967","n":"十銓","p":"284.50","cg":"6.0000","v":"8241413"},{"c":"2006","n":"東和鋼鐵","p":"69.60","cg":"0.1000","v":"8231213"},{"c":"00830","n":"國泰費城半導體","p":"100.60","cg":"3.6000","v":"8123947"},{"c":"2889","n":"國票金","p":"15.05","cg":"-0.2000","v":"8116447"},{"c":"2495","n":"普安","p":"52.10","cg":"0.0000","v":"8008101"},{"c":"6505","n":"台塑化","p":"54.00","cg":"0.5000","v":"7920372"},{"c":"4763","n":"材料*-KY","p":"45.60","cg":"1.3000","v":"7854561"},{"c":"8926","n":"台汽電","p":"79.00","cg":"0.0000","v":"7788449"},{"c":"2504","n":"國產","p":"32.80","cg":"-0.8000","v":"7781713"},{"c":"2646","n":"星宇航空","p":"20.90","cg":"-0.3500","v":"7773240"},{"c":"2606","n":"裕民","p":"62.00","cg":"0.5000","v":"7590752"},{"c":"2483","n":"百容","p":"43.60","cg":"3.9500","v":"7548022"},{"c":"1609","n":"大亞","p":"38.65","cg":"0.5000","v":"7438219"},{"c":"3041","n":"揚智","p":"30.95","cg":"2.8000","v":"7407056"},{"c":"2520","n":"冠德","p":"34.00","cg":"-2.4000","v":"7398527"},{"c":"3149","n":"正達","p":"104.50","cg":"9.5000","v":"7386968"},{"c":"3059","n":"華晶科","p":"49.35","cg":"0.5000","v":"7371472"},{"c":"2379","n":"瑞昱","p":"900.00","cg":"81.0000","v":"7335818"},{"c":"00954","n":"中信日本半導體","p":"22.69","cg":"0.8500","v":"7327763"},{"c":"1503","n":"士電","p":"245.00","cg":"3.5000","v":"7323027"},{"c":"6451","n":"訊芯-KY","p":"617.00","cg":"56.0000","v":"7203684"},{"c":"3028","n":"增你強","p":"82.50","cg":"7.5000","v":"7139869"},{"c":"6177","n":"達麗","p":"45.90","cg":"-4.5000","v":"7130141"},{"c":"00738U","n":"期元大道瓊白銀","p":"52.95","cg":"-2.6500","v":"7128738"},{"c":"2615","n":"萬海","p":"80.50","cg":"0.1000","v":"7035955"},{"c":"3015","n":"全漢","p":"65.80","cg":"4.9000","v":"6964891"},{"c":"00985A","n":"主動野村台灣50","p":"22.97","cg":"0.5000","v":"6852672"},{"c":"2605","n":"新興","p":"31.95","cg":"0.9500","v":"6769318"},{"c":"00401A","n":"主動摩根台灣鑫收","p":"14.22","cg":"0.2300","v":"6766153"},{"c":"9933","n":"中鼎","p":"43.75","cg":"1.1000","v":"6721800"},{"c":"6806","n":"森崴能源","p":"3.51","cg":"0.2700","v":"6690040"},{"c":"00662","n":"富邦NASDAQ","p":"123.15","cg":"1.3500","v":"6681286"},{"c":"6202","n":"盛群","p":"73.70","cg":"6.7000","v":"6668630"},{"c":"1563","n":"巧新","p":"66.20","cg":"-1.5000","v":"6624001"},{"c":"2451","n":"創見","p":"309.50","cg":"-2.0000","v":"6605633"},{"c":"2241","n":"艾姆勒","p":"51.60","cg":"1.0000","v":"6556715"},{"c":"00915","n":"凱基優選高股息30","p":"32.95","cg":"0.6700","v":"6480456"},{"c":"1710","n":"東聯","p":"14.15","cg":"0.5000","v":"6461350"},{"c":"00708L","n":"期元大S&P黃金正2","p":"75.90","cg":"-5.0000","v":"6403954"},{"c":"8163","n":"達方","p":"45.30","cg":"0.3500","v":"6403907"},{"c":"2338","n":"光罩","p":"54.00","cg":"0.7000","v":"6366827"},{"c":"00635U","n":"期元大S&P黃金","p":"43.71","cg":"-1.3800","v":"6323730"},{"c":"6456","n":"GIS-KY","p":"76.10","cg":"-0.3000","v":"6252638"},{"c":"00987A","n":"主動台新優勢成長","p":"18.11","cg":"0.2800","v":"6231744"},{"c":"00945B","n":"凱基美國非投等債","p":"14.44","cg":"0.0100","v":"6207636"},{"c":"3005","n":"神基","p":"100.50","cg":"-1.0000","v":"6110961"},{"c":"2328","n":"廣宇","p":"53.40","cg":"0.0000","v":"6071086"},{"c":"2331","n":"精英","p":"22.70","cg":"0.3000","v":"6061296"},{"c":"00685L","n":"群益臺灣加權正2","p":"329.55","cg":"22.8000","v":"6059202"},{"c":"3406","n":"玉晶光","p":"774.00","cg":"21.0000","v":"6000266"},{"c":"2474","n":"可成","p":"206.00","cg":"3.5000","v":"5892505"},{"c":"2349","n":"錸德","p":"14.00","cg":"0.1500","v":"5745668"},{"c":"1477","n":"聚陽","p":"213.50","cg":"-8.0000","v":"5711700"},{"c":"3062","n":"建漢","p":"25.80","cg":"-0.1500","v":"5671908"},{"c":"00916","n":"國泰全球品牌50","p":"25.37","cg":"-0.1900","v":"5585837"},{"c":"1909","n":"榮成","p":"9.95","cg":"-0.2500","v":"5582275"},{"c":"6531","n":"愛普*","p":"1115.00","cg":"0.0000","v":"5550124"},{"c":"6789","n":"采鈺","p":"555.00","cg":"12.0000","v":"5522819"},{"c":"00983A","n":"主動中信ARK創新","p":"12.05","cg":"0.1300","v":"5487657"},{"c":"1810","n":"和成","p":"21.35","cg":"1.4500","v":"5485055"},{"c":"3665","n":"貿聯-KY","p":"1990.00","cg":"-110.0000","v":"5482246"},{"c":"9910","n":"豐泰","p":"70.70","cg":"-1.9000","v":"5319463"},{"c":"1721","n":"三晃","p":"26.15","cg":"2.3500","v":"5316165"},{"c":"6278","n":"台表科","p":"206.00","cg":"1.5000","v":"5265235"},{"c":"2368","n":"金像電","p":"1395.00","cg":"40.0000","v":"5223186"},{"c":"2537","n":"聯上發","p":"11.10","cg":"-0.9000","v":"5217297"},{"c":"00642U","n":"期元大S&P石油","p":"24.55","cg":"0.4400","v":"5178019"},{"c":"00671R","n":"富邦NASDAQ反1","p":"2.37","cg":"-0.0200","v":"5172871"},{"c":"2201","n":"裕隆","p":"27.60","cg":"-0.5000","v":"5141703"},{"c":"006208","n":"富邦台50","p":"257.45","cg":"8.3500","v":"5127921"},{"c":"2374","n":"佳能","p":"74.60","cg":"-0.7000","v":"5127396"},{"c":"3376","n":"新日興","p":"209.00","cg":"4.0000","v":"5115521"},{"c":"2030","n":"彰源","p":"19.60","cg":"1.0500","v":"5105305"},{"c":"2547","n":"日勝生","p":"10.95","cg":"-0.2500","v":"5092862"},{"c":"00910","n":"第一金太空衛星","p":"65.40","cg":"-1.8500","v":"5072487"},{"c":"00913","n":"兆豐台灣晶圓製造","p":"56.55","cg":"2.6500","v":"5036572"},{"c":"6902","n":"GOGOLOOK","p":"130.50","cg":"-2.5000","v":"5010947"},{"c":"2405","n":"輔信","p":"18.90","cg":"0.0000","v":"5001150"},{"c":"6405","n":"悅城","p":"68.50","cg":"-3.0000","v":"4948148"},{"c":"6412","n":"群電","p":"95.00","cg":"3.4000","v":"4910099"},{"c":"4551","n":"智伸科","p":"226.00","cg":"4.5000","v":"4908424"},{"c":"9958","n":"世紀鋼","p":"120.00","cg":"5.0000","v":"4829127"},{"c":"6214","n":"精誠","p":"141.00","cg":"-1.0000","v":"4810505"},{"c":"2913","n":"農林","p":"11.15","cg":"0.0000","v":"4759512"},{"c":"2347","n":"聯強","p":"93.50","cg":"0.1000","v":"4759458"},{"c":"1434","n":"福懋","p":"16.90","cg":"-0.0500","v":"4717230"},{"c":"00965","n":"元大航太防衛科技","p":"25.40","cg":"-0.3400","v":"4702651"},{"c":"6901","n":"鑽石投資","p":"17.35","cg":"0.8000","v":"4672867"},{"c":"6120","n":"達運","p":"15.25","cg":"0.0000","v":"4622794"},{"c":"00995A","n":"主動中信台灣卓越","p":"18.77","cg":"0.3600","v":"4621136"},{"c":"8215","n":"明基材","p":"31.30","cg":"0.1500","v":"4604223"},{"c":"8476","n":"台境*","p":"22.85","cg":"1.1000","v":"4572286"},{"c":"4739","n":"康普","p":"128.00","cg":"0.0000","v":"4508545"},{"c":"00939","n":"統一台灣高息動能","p":"21.96","cg":"0.0100","v":"4469077"},{"c":"00952","n":"凱基台灣AI50","p":"19.04","cg":"0.4400","v":"4437631"},{"c":"2208","n":"台船","p":"18.00","cg":"0.2000","v":"4429447"},{"c":"00735","n":"國泰臺韓科技","p":"122.65","cg":"4.2500","v":"4382492"},{"c":"2476","n":"鉅祥","p":"125.50","cg":"0.5000","v":"4346629"},{"c":"00752","n":"中信中國50","p":"21.63","cg":"-0.1300","v":"4335705"},{"c":"4960","n":"誠美材","p":"29.20","cg":"0.1000","v":"4330191"},{"c":"1536","n":"和大","p":"51.60","cg":"2.9000","v":"4328430"},{"c":"5388","n":"中磊","p":"82.40","cg":"-1.8000","v":"4317474"},{"c":"6197","n":"佳必琪","p":"353.00","cg":"5.5000","v":"4317386"},{"c":"8016","n":"矽創","p":"315.00","cg":"14.5000","v":"4311857"},{"c":"00981T","n":"平衡凱基雙核收息","p":"12.32","cg":"0.1000","v":"4255358"},{"c":"4915","n":"致伸","p":"76.30","cg":"0.4000","v":"4221801"},{"c":"3504","n":"揚明光","p":"91.50","cg":"0.3000","v":"4221586"},{"c":"2385","n":"群光","p":"114.00","cg":"0.0000","v":"4219820"},{"c":"3380","n":"明泰","p":"35.80","cg":"0.8500","v":"4215799"},{"c":"3605","n":"宏致","p":"80.20","cg":"-0.3000","v":"4148335"},{"c":"2421","n":"建準","p":"150.00","cg":"5.0000","v":"4133141"},{"c":"6166","n":"凌華","p":"158.00","cg":"2.5000","v":"4123180"},{"c":"009813","n":"貝萊德標普卓越50","p":"10.99","cg":"-0.0300","v":"4071179"},{"c":"00934","n":"中信成長高股息","p":"29.14","cg":"0.4200","v":"4053055"},{"c":"3002","n":"歐格","p":"23.00","cg":"0.0500","v":"4048284"},{"c":"2481","n":"強茂","p":"176.00","cg":"16.0000","v":"4035369"},{"c":"2897","n":"王道銀行","p":"10.55","cg":"0.0500","v":"4034896"},{"c":"1608","n":"華榮","p":"35.20","cg":"0.5500","v":"4030648"},{"c":"3031","n":"佰鴻","p":"30.50","cg":"2.5000","v":"4029869"},{"c":"2915","n":"潤泰全","p":"52.60","cg":"-0.7000","v":"4028458"},{"c":"6449","n":"鈺邦","p":"428.50","cg":"-4.5000","v":"4025440"},{"c":"6862","n":"三集瑞-KY","p":"224.00","cg":"-3.0000","v":"4010370"},{"c":"00923","n":"群益台ESG低碳50","p":"44.63","cg":"1.4500","v":"4001756"},{"c":"1808","n":"潤隆","p":"30.60","cg":"-1.6500","v":"3964049"},{"c":"00648R","n":"元大S&P500反1","p":"4.02","cg":"0.0100","v":"3952260"},{"c":"3305","n":"昇貿","p":"147.00","cg":"1.0000","v":"3945720"},{"c":"00885","n":"富邦越南","p":"18.86","cg":"0.1500","v":"3931687"},{"c":"1309","n":"台達化","p":"15.05","cg":"0.3000","v":"3914441"},{"c":"1316","n":"上曜","p":"10.50","cg":"-0.4500","v":"3899422"},{"c":"00757","n":"統一FANG+","p":"130.95","cg":"2.0500","v":"3858245"},{"c":"1229","n":"聯華","p":"41.20","cg":"-0.7000","v":"3844925"},{"c":"8996","n":"高力","p":"1555.00","cg":"-35.0000","v":"3842264"},{"c":"6757","n":"台灣虎航","p":"58.90","cg":"0.7000","v":"3828808"},{"c":"6139","n":"亞翔","p":"810.00","cg":"-13.0000","v":"3816117"},{"c":"2548","n":"華固","p":"100.50","cg":"-3.0000","v":"3738172"},{"c":"5243","n":"乙盛-KY","p":"109.50","cg":"0.0000","v":"3724565"},{"c":"00951","n":"台新日本半導體","p":"21.26","cg":"0.8000","v":"3721773"},{"c":"3535","n":"晶彩科","p":"128.50","cg":"-5.5000","v":"3692494"},{"c":"1568","n":"倉佑","p":"43.30","cg":"-2.7500","v":"3678405"},{"c":"00892","n":"富邦台灣半導體","p":"47.49","cg":"1.6500","v":"3671010"},{"c":"00964","n":"中信亞太高股息","p":"14.48","cg":"-0.0500","v":"3646363"},{"c":"1904","n":"正隆","p":"22.55","cg":"0.0000","v":"3642000"},{"c":"2903","n":"遠百","p":"23.30","cg":"-0.6500","v":"3630662"},{"c":"6695","n":"芯鼎","p":"64.20","cg":"5.8000","v":"3573535"},{"c":"4576","n":"大銀微系統","p":"236.00","cg":"15.0000","v":"3565364"},{"c":"5534","n":"長虹","p":"78.90","cg":"-4.3000","v":"3495257"},{"c":"5522","n":"遠雄","p":"73.80","cg":"-0.6000","v":"3469055"},{"c":"2103","n":"台橡","p":"21.40","cg":"0.0000","v":"3468206"},{"c":"3545","n":"敦泰","p":"61.20","cg":"3.2000","v":"3453166"},{"c":"00989A","n":"主動摩根美國科技","p":"18.33","cg":"0.3200","v":"3447148"},{"c":"009811","n":"統一美國50","p":"12.84","cg":"0.0200","v":"3444759"},{"c":"2357","n":"華碩","p":"788.00","cg":"-1.0000","v":"3442620"},{"c":"8271","n":"宇瞻","p":"215.50","cg":"4.5000","v":"3426284"},{"c":"3717","n":"聯嘉投控","p":"22.20","cg":"-0.3500","v":"3417000"},{"c":"3010","n":"華立","p":"131.50","cg":"0.5000","v":"3413661"},{"c":"2345","n":"智邦","p":"2595.00","cg":"160.0000","v":"3410352"},{"c":"00865B","n":"國泰US短期公債","p":"48.16","cg":"0.1300","v":"3388058"},{"c":"2912","n":"統一超","p":"221.00","cg":"-2.5000","v":"3373046"},{"c":"3704","n":"合勤控","p":"48.50","cg":"0.2500","v":"3368218"},{"c":"3044","n":"健鼎","p":"566.00","cg":"-7.0000","v":"3357117"},{"c":"00706L","n":"期元大S&P日圓正2","p":"18.62","cg":"-0.2300","v":"3341463"},{"c":"8081","n":"致新","p":"341.50","cg":"22.5000","v":"3329927"},{"c":"5521","n":"工信","p":"10.45","cg":"-0.1500","v":"3318043"},{"c":"2049","n":"上銀","p":"343.50","cg":"8.5000","v":"3301771"},{"c":"009803","n":"玉山市值動能50","p":"22.72","cg":"0.7500","v":"3293358"},{"c":"1305","n":"華夏","p":"13.40","cg":"0.1500","v":"3287940"},{"c":"3017","n":"奇鋐","p":"2420.00","cg":"20.0000","v":"3254412"},{"c":"7788","n":"松川精密","p":"281.50","cg":"-10.5000","v":"3240548"},{"c":"2413","n":"環科","p":"56.70","cg":"0.2000","v":"3158441"},{"c":"6706","n":"惠特","p":"170.00","cg":"-2.0000","v":"3103212"},{"c":"4722","n":"國精化","p":"284.50","cg":"7.0000","v":"3090668"},{"c":"00643","n":"群益深証中小","p":"20.39","cg":"-0.0300","v":"3069972"},{"c":"00646","n":"元大S&P500","p":"74.30","cg":"0.0500","v":"3056715"},{"c":"2395","n":"研華","p":"499.50","cg":"5.5000","v":"3050140"},{"c":"3047","n":"訊舟","p":"16.20","cg":"-0.4500","v":"3029188"},{"c":"1907","n":"永豐餘","p":"27.40","cg":"-0.8000","v":"3013094"},{"c":"4952","n":"凌通","p":"60.50","cg":"2.6000","v":"3010451"},{"c":"3443","n":"創意","p":"4755.00","cg":"-105.0000","v":"2992095"},{"c":"1308","n":"亞聚","p":"14.15","cg":"0.2000","v":"2989410"},{"c":"1528","n":"恩德","p":"25.55","cg":"0.1500","v":"2976442"},{"c":"3014","n":"聯陽","p":"160.50","cg":"3.0000","v":"2926065"},{"c":"2820","n":"華票","p":"17.75","cg":"-0.1000","v":"2901647"},{"c":"6698","n":"旭暉應材","p":"44.55","cg":"2.6000","v":"2896599"},{"c":"6668","n":"中揚光","p":"45.10","cg":"-2.1000","v":"2886025"},{"c":"3591","n":"艾笛森","p":"25.95","cg":"2.0000","v":"2864473"},{"c":"3652","n":"精聯","p":"42.70","cg":"2.5000","v":"2856038"},{"c":"2023","n":"燁輝","p":"13.75","cg":"-0.2000","v":"2851176"},{"c":"4764","n":"雙鍵","p":"332.00","cg":"-6.5000","v":"2830850"},{"c":"2645","n":"長榮航太","p":"173.50","cg":"3.5000","v":"2830725"},{"c":"6753","n":"龍德造船","p":"128.00","cg":"6.5000","v":"2784390"},{"c":"3528","n":"安馳","p":"110.00","cg":"-0.5000","v":"2784370"},{"c":"2601","n":"益航","p":"5.68","cg":"-0.1300","v":"2764903"},{"c":"00904","n":"新光臺灣半導體30","p":"45.61","cg":"2.1500","v":"2758694"},{"c":"2010","n":"春源","p":"24.75","cg":"-0.1000","v":"2746510"},{"c":"1582","n":"信錦","p":"93.90","cg":"0.1000","v":"2727998"},{"c":"00907","n":"永豐優息存股","p":"16.63","cg":"-0.0300","v":"2716003"},{"c":"1455","n":"集盛","p":"9.76","cg":"-0.4400","v":"2705798"},{"c":"00924","n":"復華S&P500成長","p":"32.40","cg":"0.1000","v":"2698278"},{"c":"6446","n":"藥華藥","p":"1095.00","cg":"35.0000","v":"2689147"},{"c":"1722","n":"台肥","p":"48.00","cg":"-0.1500","v":"2684343"},{"c":"2630","n":"亞航","p":"42.90","cg":"3.0000","v":"2680376"},{"c":"7780","n":"大研生醫*","p":"18.70","cg":"0.0000","v":"2680223"},{"c":"3135","n":"凌航","p":"207.00","cg":"9.0000","v":"2680105"},{"c":"1104","n":"環泥","p":"29.00","cg":"-0.1000","v":"2678468"},{"c":"3588","n":"通嘉","p":"66.30","cg":"6.0000","v":"2676255"},{"c":"00633L","n":"富邦上証正2","p":"54.70","cg":"1.3500","v":"2668973"},{"c":"2348","n":"海悅","p":"72.00","cg":"-4.8000","v":"2659935"},{"c":"2360","n":"致茂","p":"2310.00","cg":"0.0000","v":"2655083"},{"c":"3257","n":"虹冠電","p":"67.20","cg":"6.1000","v":"2642935"},{"c":"2887I","n":"台新新光辛特","p":"9.46","cg":"-0.0400","v":"2636517"},{"c":"6799","n":"來頡","p":"109.50","cg":"9.6000","v":"2626832"},{"c":"00675L","n":"富邦臺灣加權正2","p":"364.00","cg":"25.5500","v":"2626160"},{"c":"3413","n":"京鼎","p":"321.00","cg":"-3.5000","v":"2624518"},{"c":"9914","n":"美利達","p":"73.40","cg":"1.3000","v":"2622121"},{"c":"9921","n":"巨大","p":"75.50","cg":"1.4000","v":"2611506"},{"c":"6224","n":"聚鼎","p":"83.10","cg":"-1.9000","v":"2610256"},{"c":"2428","n":"興勤","p":"311.00","cg":"-5.0000","v":"2609487"},{"c":"2455","n":"全新","p":"409.50","cg":"-6.5000","v":"2607383"},{"c":"2425","n":"承啟","p":"39.35","cg":"-0.0500","v":"2601268"},{"c":"2442","n":"新美齊","p":"19.50","cg":"-0.3500","v":"2599723"},{"c":"1476","n":"儒鴻","p":"317.00","cg":"-10.0000","v":"2587484"},{"c":"2478","n":"大毅","p":"235.50","cg":"1.5000","v":"2583511"},{"c":"2359","n":"所羅門","p":"136.50","cg":"2.5000","v":"2582242"},{"c":"2536","n":"宏普","p":"21.30","cg":"-1.0500","v":"2579265"},{"c":"00941","n":"中信上游半導體","p":"28.99","cg":"0.3900","v":"2566258"},{"c":"1515","n":"力山","p":"27.40","cg":"1.5000","v":"2537843"},{"c":"4306","n":"炎洲","p":"16.20","cg":"0.3500","v":"2531071"},{"c":"8021","n":"尖點","p":"581.00","cg":"38.0000","v":"2520341"},{"c":"3321","n":"同泰","p":"26.70","cg":"2.4000","v":"2507217"},{"c":"2393","n":"億光","p":"70.80","cg":"0.2000","v":"2492605"},{"c":"3056","n":"富華新","p":"14.90","cg":"-0.3500","v":"2481740"},{"c":"00963","n":"中信全球高股息","p":"12.42","cg":"-0.0800","v":"2473236"},{"c":"00902","n":"中信電池及儲能","p":"16.11","cg":"0.3500","v":"2454416"},{"c":"3003","n":"健和興","p":"68.50","cg":"-1.4000","v":"2419321"},{"c":"2851","n":"中再保","p":"39.30","cg":"0.3000","v":"2413002"},{"c":"8473","n":"山林水","p":"50.80","cg":"0.8000","v":"2389618"},{"c":"1440","n":"南紡","p":"13.50","cg":"0.2000","v":"2389061"},{"c":"3661","n":"世芯-KY","p":"4325.00","cg":"-55.0000","v":"2381897"},{"c":"2493","n":"揚博","p":"268.00","cg":"-5.5000","v":"2370208"},{"c":"2243","n":"宏旭-KY","p":"46.55","cg":"-5.1500","v":"2310038"},{"c":"3583","n":"辛耘","p":"889.00","cg":"0.0000","v":"2288227"},{"c":"3645","n":"達邁","p":"96.10","cg":"1.8000","v":"2278150"},{"c":"1432","n":"大魯閣","p":"18.00","cg":"0.4000","v":"2269073"},{"c":"3311","n":"閎暉","p":"40.25","cg":"1.5000","v":"2254033"},{"c":"4977","n":"眾達-KY","p":"191.00","cg":"6.5000","v":"2238478"},{"c":"3209","n":"全科","p":"62.80","cg":"0.5000","v":"2211324"},{"c":"00655L","n":"國泰中國A50正2","p":"38.19","cg":"0.9700","v":"2199741"},{"c":"2316","n":"楠梓電","p":"226.00","cg":"20.5000","v":"2199185"},{"c":"3030","n":"德律","p":"350.00","cg":"9.5000","v":"2187776"},{"c":"2838","n":"聯邦銀","p":"22.40","cg":"-0.3500","v":"2186148"},{"c":"2461","n":"光群雷","p":"18.00","cg":"-0.4000","v":"2178514"},{"c":"2104","n":"國際中橡","p":"10.40","cg":"0.0500","v":"2175233"},{"c":"4540","n":"全球傳動","p":"62.10","cg":"0.9000","v":"2166937"},{"c":"6243","n":"迅杰","p":"38.35","cg":"3.4500","v":"2144454"},{"c":"4720","n":"德淵","p":"24.55","cg":"0.3500","v":"2108408"},{"c":"3596","n":"智易","p":"188.00","cg":"-3.5000","v":"2104443"},{"c":"3437","n":"榮創","p":"23.25","cg":"1.8000","v":"2093444"},{"c":"00641R","n":"富邦日本反1","p":"3.69","cg":"-0.0300","v":"2089458"},{"c":"00852L","n":"國泰美國道瓊正2","p":"33.58","cg":"-0.3800","v":"2070680"},{"c":"2034","n":"允強","p":"20.90","cg":"0.0500","v":"2065301"},{"c":"00692","n":"富邦公司治理","p":"95.85","cg":"3.0500","v":"2061832"},{"c":"2543","n":"皇昌","p":"42.95","cg":"-1.1500","v":"2056486"},{"c":"4956","n":"光鋐","p":"39.65","cg":"1.1500","v":"2041119"},{"c":"2383","n":"台光電","p":"5825.00","cg":"225.0000","v":"2030502"},{"c":"3092","n":"鴻碩","p":"32.70","cg":"1.4000","v":"2029479"},{"c":"2534","n":"宏盛","p":"18.30","cg":"0.0000","v":"2016992"},{"c":"1444","n":"力麗","p":"7.01","cg":"-0.0300","v":"2003306"},{"c":"2637","n":"慧洋-KY","p":"77.10","cg":"-0.3000","v":"2003159"},{"c":"9946","n":"三發地產","p":"19.45","cg":"-1.1500","v":"2002077"},{"c":"6669","n":"緯穎","p":"4855.00","cg":"0.0000","v":"2000502"},{"c":"2365","n":"昆盈","p":"34.40","cg":"0.3500","v":"1993966"},{"c":"3013","n":"晟銘電","p":"113.50","cg":"0.5000","v":"1981144"},{"c":"1597","n":"直得","p":"157.50","cg":"-0.5000","v":"1979394"},{"c":"3023","n":"信邦","p":"333.00","cg":"5.5000","v":"1974886"},{"c":"1519","n":"華城","p":"831.00","cg":"-2.0000","v":"1969787"},{"c":"3694","n":"海華","p":"62.00","cg":"1.2000","v":"1967197"},{"c":"2429","n":"銘旺科","p":"42.30","cg":"3.7500","v":"1939088"},{"c":"3703","n":"欣陸","p":"21.45","cg":"-0.3500","v":"1912340"},{"c":"009800","n":"中信NASDAQ","p":"13.32","cg":"0.1400","v":"1911769"},{"c":"3051","n":"力特","p":"27.90","cg":"0.0500","v":"1910698"},{"c":"00905","n":"FT臺灣Smart","p":"29.38","cg":"0.9600","v":"1910628"},{"c":"2404","n":"漢唐","p":"1280.00","cg":"15.0000","v":"1898021"},{"c":"3592","n":"瑞鼎","p":"285.00","cg":"10.0000","v":"1886905"},{"c":"5434","n":"崇越","p":"506.00","cg":"30.5000","v":"1874532"},{"c":"3008","n":"大立光","p":"5185.00","cg":"-10.0000","v":"1874016"},{"c":"2009","n":"第一銅","p":"39.60","cg":"0.1000","v":"1873512"},{"c":"3346","n":"麗清","p":"25.00","cg":"1.3000","v":"1851032"},{"c":"2439","n":"美律","p":"92.80","cg":"0.4000","v":"1838807"},{"c":"1560","n":"中砂","p":"713.00","cg":"13.0000","v":"1830864"},{"c":"00894","n":"中信小資高價30","p":"51.60","cg":"1.5000","v":"1826671"},{"c":"6189","n":"豐藝","p":"54.60","cg":"-0.3000","v":"1826148"},{"c":"3055","n":"蔚華科","p":"92.00","cg":"0.9000","v":"1818799"},{"c":"8162","n":"微矽電子-創","p":"86.20","cg":"7.8000","v":"1803891"},{"c":"6152","n":"百一","p":"14.20","cg":"-0.3000","v":"1798299"},{"c":"00700","n":"富邦恒生國企","p":"15.96","cg":"-0.1400","v":"1782107"},{"c":"2539","n":"櫻花建","p":"38.65","cg":"-1.3000","v":"1776165"},{"c":"009817","n":"國泰日本不動產","p":"8.59","cg":"-0.0600","v":"1774215"},{"c":"2392","n":"正崴","p":"40.05","cg":"0.3000","v":"1774191"},{"c":"6142","n":"友勁","p":"9.55","cg":"-0.0600","v":"1762282"},{"c":"2467","n":"志聖","p":"630.00","cg":"31.0000","v":"1743491"},{"c":"2362","n":"藍天","p":"47.20","cg":"-0.3500","v":"1743168"},{"c":"009809","n":"富邦淨零ESG50","p":"18.33","cg":"0.6600","v":"1724545"},{"c":"00639","n":"富邦深100","p":"18.91","cg":"0.2200","v":"1718102"},{"c":"1612","n":"宏泰","p":"38.25","cg":"-0.0500","v":"1707601"},{"c":"00936","n":"台新永續高息中小","p":"20.80","cg":"0.2000","v":"1700120"},{"c":"00938","n":"凱基優選30","p":"25.12","cg":"0.0600","v":"1675500"},{"c":"5608","n":"四維航","p":"14.80","cg":"-0.1000","v":"1672344"},{"c":"6585","n":"鼎基","p":"150.50","cg":"12.5000","v":"1663809"},{"c":"6831","n":"邁科","p":"817.00","cg":"44.0000","v":"1654202"},{"c":"3518","n":"柏騰","p":"30.90","cg":"2.5500","v":"1648973"},{"c":"4961","n":"天鈺","p":"177.50","cg":"3.5000","v":"1636642"},{"c":"00930","n":"永豐ESG低碳高息","p":"26.19","cg":"0.6800","v":"1635806"},{"c":"3026","n":"禾伸堂","p":"897.00","cg":"0.0000","v":"1632169"},{"c":"1210","n":"大成","p":"54.70","cg":"0.0000","v":"1631362"},{"c":"2511","n":"太子","p":"8.11","cg":"-0.1100","v":"1626121"},{"c":"2530","n":"華建","p":"19.00","cg":"-1.0000","v":"1618786"},{"c":"1447","n":"力鵬","p":"6.02","cg":"-0.0100","v":"1604966"},{"c":"00932","n":"兆豐永續高息等權","p":"17.87","cg":"0.1900","v":"1603012"},{"c":"1709","n":"和益","p":"21.50","cg":"0.2500","v":"1581613"},{"c":"6442","n":"光聖","p":"2085.00","cg":"140.0000","v":"1557238"},{"c":"3024","n":"憶聲","p":"12.50","cg":"0.3000","v":"1549998"},{"c":"6164","n":"華興","p":"13.70","cg":"0.3500","v":"1543118"},{"c":"8213","n":"志超","p":"37.35","cg":"0.1500","v":"1539623"},{"c":"00909","n":"國泰數位支付服務","p":"51.30","cg":"0.1500","v":"1538772"},{"c":"4968","n":"立積","p":"118.00","cg":"4.5000","v":"1538712"},{"c":"2460","n":"建通","p":"35.05","cg":"0.2500","v":"1538506"},{"c":"1449","n":"佳和","p":"14.35","cg":"0.3000","v":"1537281"},{"c":"2419","n":"仲琦","p":"29.45","cg":"0.0000","v":"1536622"},{"c":"6205","n":"詮欣","p":"84.10","cg":"2.8000","v":"1535635"},{"c":"1795","n":"美時","p":"191.50","cg":"-1.5000","v":"1532359"},{"c":"2465","n":"麗臺","p":"79.40","cg":"-1.5000","v":"1523191"},{"c":"6994","n":"富威電力","p":"53.40","cg":"0.2000","v":"1522008"},{"c":"00893","n":"國泰智能電動車","p":"47.43","cg":"0.8100","v":"1504317"},{"c":"6472","n":"保瑞","p":"423.00","cg":"0.5000","v":"1500221"},{"c":"6550","n":"北極星藥業-KY","p":"13.20","cg":"-0.4500","v":"1497424"},{"c":"6196","n":"帆宣","p":"562.00","cg":"-5.0000","v":"1496826"},{"c":"6226","n":"光鼎","p":"12.50","cg":"0.1000","v":"1486940"},{"c":"4142","n":"國光生","p":"17.20","cg":"-0.2000","v":"1477481"},{"c":"2417","n":"圓剛","p":"46.90","cg":"0.8000","v":"1471657"},{"c":"3011","n":"今皓","p":"14.30","cg":"-0.2500","v":"1456187"},{"c":"2434","n":"統懋","p":"42.70","cg":"3.8500","v":"1451272"},{"c":"3653","n":"健策","p":"3840.00","cg":"-125.0000","v":"1448778"},{"c":"3296","n":"勝德","p":"30.70","cg":"0.9000","v":"1445952"},{"c":"9939","n":"宏全","p":"131.50","cg":"-2.5000","v":"1424410"},{"c":"3058","n":"立德","p":"9.65","cg":"0.2500","v":"1412799"},{"c":"1626","n":"艾美特-KY","p":"9.74","cg":"-0.2300","v":"1410964"},{"c":"2466","n":"冠西電","p":"55.10","cg":"5.0000","v":"1402215"},{"c":"8261","n":"富鼎","p":"236.50","cg":"21.5000","v":"1392680"},{"c":"6861","n":"睿生光電","p":"378.50","cg":"7.5000","v":"1385169"},{"c":"6670","n":"復盛應用","p":"291.00","cg":"3.5000","v":"1381070"},{"c":"00949","n":"復華日本龍頭","p":"20.81","cg":"0.0300","v":"1379842"},{"c":"00670L","n":"富邦NASDAQ正2","p":"218.00","cg":"3.8000","v":"1367825"},{"c":"6141","n":"柏承","p":"35.60","cg":"0.7500","v":"1365880"},{"c":"9103","n":"美德醫療-DR","p":"5.25","cg":"-0.0800","v":"1364602"},{"c":"00983D","n":"主動富邦複合收益","p":"10.11","cg":"-0.0100","v":"1362333"},{"c":"4934","n":"太極","p":"17.40","cg":"0.3000","v":"1361968"},{"c":"6781","n":"AES-KY","p":"1205.00","cg":"25.0000","v":"1356985"},{"c":"3701","n":"大眾控","p":"48.35","cg":"-0.1000","v":"1333040"},{"c":"0055","n":"元大MSCI金融","p":"42.92","cg":"-0.5400","v":"1331867"},{"c":"8210","n":"勤誠","p":"1370.00","cg":"5.0000","v":"1326115"},{"c":"3021","n":"鴻名","p":"30.30","cg":"-0.7000","v":"1321959"},{"c":"7795","n":"長廣","p":"451.00","cg":"41.0000","v":"1320640"},{"c":"4766","n":"南寶","p":"372.00","cg":"0.0000","v":"1311880"},{"c":"5538","n":"東明-KY","p":"32.30","cg":"0.3000","v":"1302764"},{"c":"9941","n":"裕融","p":"81.80","cg":"0.4000","v":"1302228"},{"c":"2106","n":"建大","p":"17.25","cg":"0.0000","v":"1302124"},{"c":"1529","n":"樂事綠能","p":"22.70","cg":"-0.2000","v":"1299557"},{"c":"9938","n":"百和","p":"44.05","cg":"0.0500","v":"1297885"},{"c":"8114","n":"振樺電","p":"211.50","cg":"-0.5000","v":"1275421"},{"c":"2022","n":"聚亨","p":"7.85","cg":"0.1300","v":"1275328"},{"c":"2258","n":"鴻華先進-創","p":"34.20","cg":"1.2000","v":"1271488"},{"c":"4532","n":"瑞智","p":"24.20","cg":"0.4500","v":"1262955"},{"c":"7827","n":"漢康-KY創","p":"159.00","cg":"-5.5000","v":"1262383"},{"c":"8072","n":"陞泰","p":"31.25","cg":"1.8500","v":"1248284"},{"c":"00669R","n":"國泰美國道瓊反1","p":"5.33","cg":"0.0300","v":"1244510"},{"c":"1522","n":"堤維西","p":"31.35","cg":"-0.7500","v":"1232144"},{"c":"9917","n":"中保科","p":"116.50","cg":"-0.5000","v":"1230882"},{"c":"6414","n":"樺漢","p":"381.00","cg":"-2.0000","v":"1228699"},{"c":"9934","n":"成霖","p":"10.35","cg":"0.1500","v":"1227178"},{"c":"2038","n":"海光","p":"13.90","cg":"0.0500","v":"1223340"},{"c":"2233","n":"宇隆","p":"315.50","cg":"10.0000","v":"1207023"},{"c":"7769","n":"鴻勁","p":"6915.00","cg":"-60.0000","v":"1204698"},{"c":"2420","n":"新巨","p":"64.20","cg":"3.0000","v":"1203873"},{"c":"009801","n":"中信美國創新科技","p":"12.62","cg":"0.2000","v":"1199267"},{"c":"3050","n":"鈺德","p":"12.95","cg":"-0.0500","v":"1190262"},{"c":"6526","n":"達發","p":"705.00","cg":"9.0000","v":"1189990"},{"c":"2527","n":"宏璟","p":"39.25","cg":"-0.5500","v":"1189522"},{"c":"6715","n":"嘉基","p":"518.00","cg":"46.5000","v":"1188042"},{"c":"6589","n":"台康生技","p":"46.25","cg":"-0.2000","v":"1173601"},{"c":"1307","n":"三芳","p":"36.40","cg":"0.0000","v":"1172044"},{"c":"00701","n":"國泰股利精選30","p":"39.90","cg":"0.5200","v":"1165792"},{"c":"4164","n":"承業醫","p":"30.40","cg":"-0.7500","v":"1157953"},{"c":"9919","n":"康那香","p":"13.90","cg":"-0.1000","v":"1151072"},{"c":"9136","n":"巨騰-DR","p":"15.95","cg":"-0.7500","v":"1150013"},{"c":"6206","n":"飛捷","p":"134.50","cg":"3.0000","v":"1144815"},{"c":"8222","n":"寶一","p":"36.90","cg":"1.6500","v":"1134303"},{"c":"8464","n":"億豐","p":"346.00","cg":"-12.0000","v":"1132815"},{"c":"5222","n":"全訊","p":"125.00","cg":"11.0000","v":"1127038"},{"c":"00636","n":"國泰中國A50","p":"29.43","cg":"0.3800","v":"1126231"},{"c":"6805","n":"富世達","p":"1820.00","cg":"65.0000","v":"1121658"},{"c":"2540","n":"愛山林","p":"53.40","cg":"-1.7000","v":"1113017"},{"c":"1723","n":"中碳","p":"89.50","cg":"2.5000","v":"1097511"},{"c":"6944","n":"兆聯實業","p":"1070.00","cg":"25.0000","v":"1092999"},{"c":"2836","n":"高雄銀","p":"12.30","cg":"-0.0500","v":"1084491"},{"c":"009804","n":"聯邦台精彩50","p":"25.09","cg":"0.7200","v":"1079397"},{"c":"2206","n":"三陽工業","p":"60.60","cg":"-1.0000","v":"1071057"},{"c":"00850","n":"元大臺灣ESG永續","p":"95.00","cg":"2.5500","v":"1070642"},{"c":"1618","n":"合機","p":"42.35","cg":"0.5500","v":"1067418"},{"c":"6830","n":"汎銓","p":"608.00","cg":"44.0000","v":"1057582"},{"c":"5519","n":"隆大","p":"33.55","cg":"-0.9000","v":"1055939"},{"c":"2731","n":"雄獅","p":"151.50","cg":"-0.5000","v":"1045539"},{"c":"8438","n":"昶昕","p":"92.10","cg":"-0.4000","v":"1042737"},{"c":"1342","n":"八貫","p":"117.00","cg":"1.0000","v":"1035325"},{"c":"1227","n":"佳格","p":"29.10","cg":"0.0000","v":"1033723"},{"c":"3022","n":"威強電","p":"83.20","cg":"-1.3000","v":"1023350"},{"c":"3501","n":"維熹","p":"40.90","cg":"-0.9000","v":"1019868"},{"c":"2390","n":"云辰","p":"12.15","cg":"-0.2000","v":"1011317"},{"c":"1532","n":"勤美","p":"23.30","cg":"-0.7000","v":"1007466"},{"c":"2491","n":"吉祥全","p":"44.00","cg":"3.0000","v":"1005828"},{"c":"00917","n":"中信特選金融","p":"22.32","cg":"-0.2900","v":"1000945"},{"c":"3029","n":"零壹","p":"101.50","cg":"0.0000","v":"999817"},{"c":"3338","n":"泰碩","p":"75.80","cg":"0.6000","v":"993048"},{"c":"9940","n":"信義","p":"19.40","cg":"-0.4500","v":"992520"},{"c":"1611","n":"中電","p":"13.40","cg":"0.4000","v":"986618"},{"c":"3708","n":"上緯投控","p":"115.50","cg":"-1.0000","v":"983541"},{"c":"7610","n":"聯友金屬-創","p":"2505.00","cg":"190.0000","v":"974501"},{"c":"8454","n":"富邦媒","p":"335.00","cg":"-6.0000","v":"971943"},{"c":"6426","n":"統新","p":"217.00","cg":"6.5000","v":"969931"},{"c":"2059","n":"川湖","p":"7550.00","cg":"685.0000","v":"967008"},{"c":"2883B","n":"凱基金乙特","p":"8.26","cg":"0.0000","v":"961158"},{"c":"6215","n":"和椿","p":"109.50","cg":"1.0000","v":"957006"},{"c":"2108","n":"南帝","p":"28.75","cg":"0.0500","v":"956957"},{"c":"1712","n":"興農","p":"39.05","cg":"-0.2500","v":"955269"},{"c":"3532","n":"台勝科","p":"378.50","cg":"-11.5000","v":"951684"},{"c":"6108","n":"競國","p":"19.10","cg":"-0.2500","v":"947918"},{"c":"2020","n":"美亞","p":"21.75","cg":"0.0000","v":"942328"},{"c":"2032","n":"新鋼","p":"17.95","cg":"0.3500","v":"941232"},{"c":"00962","n":"台新AI優息動能","p":"15.21","cg":"0.2100","v":"934103"},{"c":"3530","n":"晶相光","p":"73.40","cg":"2.3000","v":"932860"},{"c":"6768","n":"志強-KY","p":"88.50","cg":"2.8000","v":"932801"},{"c":"00763U","n":"期街口道瓊銅","p":"33.89","cg":"-0.3100","v":"922580"},{"c":"1524","n":"耿鼎","p":"29.70","cg":"-0.2500","v":"920772"},{"c":"00731","n":"復華富時高息低波","p":"91.60","cg":"0.0500","v":"919926"},{"c":"5515","n":"建國","p":"42.00","cg":"0.0000","v":"919377"},{"c":"4564","n":"元翎","p":"15.80","cg":"0.0000","v":"912727"},{"c":"2204","n":"中華","p":"55.10","cg":"-0.2000","v":"904383"},{"c":"2617","n":"台航","p":"30.05","cg":"0.2000","v":"902444"},{"c":"1460","n":"宏遠","p":"7.15","cg":"-0.0500","v":"900883"},{"c":"1218","n":"泰山","p":"17.80","cg":"-0.1000","v":"898276"},{"c":"7799","n":"禾榮科","p":"386.00","cg":"24.0000","v":"885365"},{"c":"6579","n":"研揚","p":"167.50","cg":"-0.5000","v":"882206"},{"c":"6573","n":"虹揚-KY","p":"17.80","cg":"1.6000","v":"881547"},{"c":"911868","n":"同方友友-DR","p":"1.27","cg":"0.0000","v":"881059"},{"c":"00926","n":"凱基全球菁英55","p":"24.98","cg":"0.1700","v":"862288"},{"c":"1436","n":"華友聯","p":"45.70","cg":"-1.8000","v":"852993"},{"c":"6438","n":"迅得","p":"159.50","cg":"0.5000","v":"852455"},{"c":"1590","n":"亞德客-KY","p":"1395.00","cg":"15.0000","v":"847669"},{"c":"2431","n":"聯昌","p":"11.75","cg":"0.1000","v":"846821"},{"c":"6658","n":"聯策","p":"184.50","cg":"-4.5000","v":"842831"},{"c":"2497","n":"怡利電","p":"59.40","cg":"-0.8000","v":"837374"},{"c":"912000","n":"晨訊科-DR","p":"2.71","cg":"0.0100","v":"836255"},{"c":"5269","n":"祥碩","p":"1450.00","cg":"-5.0000","v":"833855"},{"c":"3032","n":"偉訓","p":"85.00","cg":"-0.9000","v":"832832"},{"c":"6133","n":"金橋","p":"23.35","cg":"0.3000","v":"831558"},{"c":"2031","n":"新光鋼","p":"38.95","cg":"-0.1000","v":"826929"},{"c":"1789","n":"神隆","p":"20.40","cg":"-0.1500","v":"826139"},{"c":"1215","n":"卜蜂","p":"115.00","cg":"0.0000","v":"815664"},{"c":"1416","n":"廣豐","p":"10.95","cg":"-0.1500","v":"808104"},{"c":"1471","n":"首利","p":"11.15","cg":"0.2000","v":"807719"},{"c":"00920","n":"富邦ESG綠色電力","p":"26.88","cg":"0.5600","v":"797250"},{"c":"3356","n":"奇偶","p":"61.50","cg":"1.1000","v":"794079"},{"c":"2017","n":"官田鋼","p":"9.36","cg":"0.0300","v":"787353"},{"c":"3533","n":"嘉澤","p":"2315.00","cg":"25.0000","v":"785073"},{"c":"2444","n":"兆勁","p":"13.40","cg":"0.0000","v":"780341"},{"c":"2440","n":"太空梭","p":"16.95","cg":"0.0000","v":"772176"},{"c":"6235","n":"華孚","p":"41.30","cg":"0.7500","v":"769191"},{"c":"4949","n":"有成精密","p":"89.20","cg":"0.7000","v":"761128"},{"c":"7721","n":"微程式","p":"77.00","cg":"1.9000","v":"752876"},{"c":"2905","n":"三商","p":"15.15","cg":"0.0000","v":"751143"},{"c":"006205","n":"富邦上証","p":"41.95","cg":"0.4100","v":"747987"},{"c":"00733","n":"富邦臺灣中小","p":"80.35","cg":"2.1000","v":"744090"},{"c":"5531","n":"鄉林","p":"8.09","cg":"-0.1800","v":"739567"},{"c":"5484","n":"慧友","p":"47.10","cg":"0.1000","v":"731300"},{"c":"3563","n":"牧德","p":"728.00","cg":"13.0000","v":"729884"},{"c":"8011","n":"台通","p":"18.05","cg":"0.0500","v":"725627"},{"c":"5284","n":"jpp-KY","p":"400.00","cg":"-5.0000","v":"724592"},{"c":"5258","n":"虹堡","p":"51.30","cg":"0.7000","v":"722021"},{"c":"2614","n":"東森","p":"18.65","cg":"-0.2000","v":"721372"},{"c":"6605","n":"帝寶","p":"140.00","cg":"-1.5000","v":"718132"},{"c":"6756","n":"威鋒電子","p":"108.00","cg":"4.5000","v":"717323"},{"c":"2882A","n":"國泰特","p":"62.00","cg":"-0.1000","v":"716413"},{"c":"4912","n":"聯德控股-KY","p":"89.90","cg":"1.2000","v":"715280"},{"c":"1707","n":"葡萄王","p":"98.70","cg":"-1.0000","v":"713970"},{"c":"3515","n":"華擎","p":"246.00","cg":"-0.5000","v":"713844"},{"c":"2753","n":"八方雲集","p":"190.00","cg":"3.0000","v":"710882"},{"c":"8103","n":"瀚荃","p":"97.10","cg":"0.0000","v":"710854"},{"c":"2538","n":"基泰","p":"10.00","cg":"-0.1000","v":"707005"},{"c":"00693U","n":"期街口S&P黃豆","p":"20.86","cg":"-0.0900","v":"704631"},{"c":"9802","n":"鈺齊-KY","p":"75.80","cg":"-1.4000","v":"699887"},{"c":"3712","n":"永崴投控","p":"18.05","cg":"0.4000","v":"697487"},{"c":"00911","n":"兆豐洲際半導體","p":"67.80","cg":"2.7500","v":"696075"},{"c":"1736","n":"喬山","p":"116.00","cg":"-3.5000","v":"693075"},{"c":"1337","n":"再生-KY","p":"5.05","cg":"-0.0200","v":"691681"},{"c":"2832","n":"台產","p":"56.50","cg":"0.2000","v":"685375"},{"c":"3607","n":"谷崧","p":"16.95","cg":"0.1000","v":"684827"},{"c":"6165","n":"浪凡","p":"48.00","cg":"-0.6000","v":"680100"},{"c":"2069","n":"運錩","p":"19.05","cg":"0.2500","v":"680018"},{"c":"00876","n":"元大全球5G","p":"103.80","cg":"2.1500","v":"676228"},{"c":"009818","n":"華南永昌NASDAQxT","p":"20.06","cg":"0.3000","v":"674747"},{"c":"6409","n":"旭隼","p":"943.00","cg":"17.0000","v":"668836"},{"c":"4169","n":"泰宗","p":"184.50","cg":"16.5000","v":"667897"},{"c":"3027","n":"盛達","p":"21.55","cg":"0.5500","v":"667446"},{"c":"6691","n":"洋基工程","p":"728.00","cg":"8.0000","v":"667129"},{"c":"009812","n":"野村日本東證","p":"12.59","cg":"0.0700","v":"664436"},{"c":"00898","n":"國泰基因免疫革命","p":"8.45","cg":"-0.0100","v":"664112"},{"c":"2462","n":"良得電","p":"25.50","cg":"0.0500","v":"655652"},{"c":"6541","n":"泰福-KY","p":"42.55","cg":"2.1000","v":"655088"},{"c":"3138","n":"耀登","p":"138.00","cg":"1.5000","v":"651912"},{"c":"7711","n":"永擎","p":"356.00","cg":"-8.5000","v":"649439"},{"c":"2528","n":"皇普","p":"21.70","cg":"-0.7000","v":"645051"},{"c":"6552","n":"易華電","p":"33.05","cg":"2.0000","v":"639955"},{"c":"4566","n":"時碩工業","p":"65.60","cg":"0.8000","v":"634342"},{"c":"6112","n":"邁達特","p":"45.40","cg":"0.2000","v":"628323"},{"c":"00944","n":"野村趨勢動能高息","p":"22.54","cg":"0.3700","v":"624700"},{"c":"8429","n":"金麗-KY","p":"6.39","cg":"-0.1200","v":"623074"},{"c":"3543","n":"州巧","p":"30.95","cg":"0.0000","v":"614494"},{"c":"1773","n":"勝一","p":"178.50","cg":"-1.5000","v":"613399"},{"c":"1464","n":"得力","p":"10.20","cg":"-0.1000","v":"611883"},{"c":"2852","n":"第一保","p":"26.30","cg":"-0.0500","v":"611287"},{"c":"6885","n":"全福生技","p":"21.70","cg":"-0.7000","v":"611210"},{"c":"8249","n":"菱光","p":"52.20","cg":"0.1000","v":"611052"},{"c":"3046","n":"建碁","p":"57.10","cg":"0.3000","v":"608832"},{"c":"00912","n":"中信臺灣智慧50","p":"35.82","cg":"1.0800","v":"603103"},{"c":"2015","n":"豐興","p":"61.00","cg":"0.3000","v":"597745"},{"c":"4414","n":"如興","p":"8.39","cg":"-0.0500","v":"593470"},{"c":"1734","n":"杏輝","p":"32.10","cg":"0.2000","v":"592480"},{"c":"1325","n":"恆大","p":"25.60","cg":"-0.5000","v":"589319"},{"c":"2505","n":"國揚","p":"18.50","cg":"-0.3000","v":"588535"},{"c":"2453","n":"凌群","p":"57.50","cg":"0.9000","v":"579610"},{"c":"4746","n":"台耀","p":"52.50","cg":"0.2000","v":"576439"},{"c":"3040","n":"遠見","p":"39.05","cg":"0.6500","v":"576200"},{"c":"0061","n":"元大寶滬深","p":"25.79","cg":"0.2900","v":"575857"},{"c":"5607","n":"遠雄港","p":"52.20","cg":"0.4000","v":"572954"},{"c":"3167","n":"大量","p":"805.00","cg":"-15.0000","v":"566499"},{"c":"2397","n":"友通","p":"61.60","cg":"0.8000","v":"564961"},{"c":"6558","n":"興能高","p":"31.45","cg":"0.5500","v":"560942"},{"c":"1467","n":"南緯","p":"7.15","cg":"-0.1300","v":"559940"},{"c":"2468","n":"華經","p":"38.10","cg":"0.1000","v":"558986"},{"c":"6873","n":"泓德能源","p":"81.80","cg":"3.0000","v":"558763"},{"c":"00645","n":"富邦日本","p":"57.85","cg":"0.5500","v":"555464"},{"c":"2597","n":"潤弘","p":"173.50","cg":"-4.5000","v":"551366"},{"c":"8374","n":"羅昇","p":"92.50","cg":"1.5000","v":"548759"},{"c":"1217","n":"愛之味","p":"9.89","cg":"0.0100","v":"548184"},{"c":"4807","n":"日成-KY","p":"43.95","cg":"-0.0500","v":"546561"},{"c":"2107","n":"厚生","p":"25.75","cg":"0.3500","v":"542955"},{"c":"00956","n":"中信日經高股息","p":"12.31","cg":"-0.0500","v":"542104"},{"c":"6533","n":"晶心科","p":"207.00","cg":"5.5000","v":"539728"},{"c":"2072","n":"世紀風電","p":"175.50","cg":"1.5000","v":"538755"},{"c":"2314","n":"台揚","p":"14.35","cg":"-0.6000","v":"532506"},{"c":"2535","n":"達欣工","p":"93.80","cg":"0.1000","v":"531100"},{"c":"2509","n":"全坤建","p":"13.70","cg":"-0.8500","v":"530712"},{"c":"1616","n":"億泰","p":"22.25","cg":"0.1000","v":"530336"},{"c":"2025","n":"千興","p":"14.10","cg":"0.0000","v":"529865"},{"c":"5907","n":"大洋-KY","p":"5.05","cg":"-0.0500","v":"527050"},{"c":"00986A","n":"主動台新龍頭成長","p":"15.63","cg":"0.2800","v":"527004"},{"c":"2033","n":"佳大","p":"16.90","cg":"1.1500","v":"526433"},{"c":"2480","n":"敦陽科","p":"154.50","cg":"1.0000","v":"522640"},{"c":"4582","n":"聚恆-創","p":"26.25","cg":"-0.3000","v":"522229"},{"c":"6477","n":"安集","p":"32.40","cg":"0.3500","v":"519804"},{"c":"6909","n":"創控","p":"55.90","cg":"5.0000","v":"516485"},{"c":"1323","n":"永裕","p":"20.00","cg":"0.2000","v":"508419"},{"c":"2427","n":"三商電","p":"22.20","cg":"-0.1000","v":"506683"},{"c":"1108","n":"幸福","p":"13.90","cg":"0.0000","v":"504876"},{"c":"1517","n":"利奇","p":"10.50","cg":"0.0000","v":"504649"},{"c":"2211","n":"長榮鋼","p":"94.80","cg":"-0.7000","v":"504196"},{"c":"1201","n":"味全","p":"12.45","cg":"-0.1000","v":"503986"},{"c":"3025","n":"星通","p":"71.50","cg":"0.5000","v":"502930"},{"c":"6869","n":"雲豹能源","p":"77.30","cg":"0.0000","v":"501067"},{"c":"1219","n":"福壽","p":"12.50","cg":"-0.1000","v":"499989"},{"c":"4555","n":"氣立","p":"48.65","cg":"0.8000","v":"499035"},{"c":"1459","n":"聯發","p":"11.70","cg":"-0.1000","v":"498967"},{"c":"3052","n":"夆典","p":"10.75","cg":"-0.1000","v":"494380"},{"c":"4178","n":"永笙-KY","p":"17.20","cg":"-0.4500","v":"493062"},{"c":"00895","n":"富邦未來車","p":"53.15","cg":"0.9000","v":"491293"},{"c":"2231","n":"為升","p":"94.30","cg":"1.4000","v":"486564"},{"c":"2850","n":"新產","p":"143.00","cg":"1.0000","v":"482839"},{"c":"2007","n":"燁興","p":"7.45","cg":"0.0600","v":"479632"},{"c":"4104","n":"佳醫","p":"68.80","cg":"-0.7000","v":"477973"},{"c":"7749","n":"意騰-KY","p":"478.50","cg":"-6.0000","v":"477234"},{"c":"3229","n":"晟鈦","p":"45.00","cg":"-0.7500","v":"475791"},{"c":"2414","n":"精技","p":"63.30","cg":"0.5000","v":"475526"},{"c":"2207","n":"和泰車","p":"481.00","cg":"-1.0000","v":"475516"},{"c":"3004","n":"豐達科","p":"138.00","cg":"3.5000","v":"474278"},{"c":"4562","n":"穎漢","p":"35.55","cg":"0.3000","v":"474056"},{"c":"00897","n":"富邦基因免疫生技","p":"10.06","cg":"-0.0400","v":"473590"},{"c":"3419","n":"譁裕","p":"14.30","cg":"-0.1000","v":"472168"},{"c":"4545","n":"銘鈺","p":"39.35","cg":"2.2500","v":"470227"},{"c":"7822","n":"倍利科","p":"1220.00","cg":"55.0000","v":"464953"},{"c":"2611","n":"志信","p":"13.85","cg":"-0.1500","v":"460713"},{"c":"00971","n":"野村美國研發龍頭","p":"16.73","cg":"0.0600","v":"456757"},{"c":"9906","n":"欣巴巴","p":"43.70","cg":"-3.1000","v":"456278"},{"c":"1603","n":"華電","p":"31.55","cg":"-0.1500","v":"455523"},{"c":"6136","n":"富爾特","p":"25.20","cg":"-0.1000","v":"455173"},{"c":"6854","n":"錼創科技-KY創","p":"132.50","cg":"2.5000","v":"452113"},{"c":"2727","n":"王品","p":"246.50","cg":"0.0000","v":"450753"},{"c":"2636","n":"台驊控股","p":"70.70","cg":"0.5000","v":"449738"},{"c":"3038","n":"全台","p":"22.95","cg":"0.1000","v":"443699"},{"c":"1762","n":"中化生","p":"35.80","cg":"0.3000","v":"443314"},{"c":"00690","n":"兆豐藍籌30","p":"84.95","cg":"2.6500","v":"442201"},{"c":"006207","n":"復華滬深","p":"34.59","cg":"0.3900","v":"441454"},{"c":"00982D","n":"主動富邦動態入息","p":"9.95","cg":"-0.0200","v":"440023"},{"c":"2516","n":"新建","p":"13.45","cg":"0.1000","v":"438071"},{"c":"2911","n":"麗嬰房","p":"7.88","cg":"-0.1300","v":"436691"},{"c":"00921","n":"兆豐龍頭等權重","p":"23.85","cg":"0.5300","v":"436246"},{"c":"1540","n":"喬福","p":"22.00","cg":"0.1000","v":"435651"},{"c":"5706","n":"鳳凰","p":"54.10","cg":"0.1000","v":"434048"},{"c":"1735","n":"日勝化","p":"23.20","cg":"0.0000","v":"422961"},{"c":"6592","n":"和潤企業","p":"65.70","cg":"0.4000","v":"422710"},{"c":"1442","n":"名軒","p":"27.40","cg":"-0.6000","v":"418056"},{"c":"2545","n":"皇翔","p":"37.85","cg":"-0.7000","v":"414461"},{"c":"4426","n":"利勤","p":"7.81","cg":"-0.1700","v":"411932"},{"c":"6024","n":"群益期","p":"62.00","cg":"0.0000","v":"408348"},{"c":"00652","n":"富邦印度","p":"33.00","cg":"0.0700","v":"407013"},{"c":"2102","n":"泰豐","p":"18.05","cg":"-0.3000","v":"406713"},{"c":"2816","n":"旺旺保","p":"33.80","cg":"0.3500","v":"402683"},{"c":"9955","n":"佳龍","p":"27.10","cg":"0.1500","v":"400837"},{"c":"5525","n":"順天","p":"21.80","cg":"-0.7500","v":"399154"},{"c":"00960","n":"野村全球航運龍頭","p":"17.39","cg":"0.0000","v":"395293"},{"c":"2012","n":"春雨","p":"15.30","cg":"0.7000","v":"390107"},{"c":"1776","n":"展宇","p":"19.20","cg":"0.4500","v":"387090"},{"c":"009808","n":"華南永昌優選50","p":"33.02","cg":"1.0200","v":"385983"},{"c":"1232","n":"大統益","p":"142.00","cg":"-1.0000","v":"385597"},{"c":"4590","n":"富田-創","p":"80.40","cg":"2.4000","v":"385176"},{"c":"6776","n":"展碁國際","p":"59.10","cg":"-0.2000","v":"384957"},{"c":"6928","n":"攸泰科技","p":"49.50","cg":"1.5500","v":"384462"},{"c":"1103","n":"嘉泥","p":"13.75","cg":"-0.0500","v":"379918"},{"c":"2387","n":"精元","p":"39.85","cg":"0.3500","v":"379394"},{"c":"00899","n":"FT潔淨能源","p":"26.61","cg":"0.4800","v":"376956"},{"c":"2607","n":"榮運","p":"49.55","cg":"0.0000","v":"376002"},{"c":"4770","n":"上品","p":"216.00","cg":"0.5000","v":"372579"},{"c":"1506","n":"正道","p":"10.20","cg":"-0.1000","v":"371264"},{"c":"1604","n":"聲寶","p":"23.15","cg":"0.0000","v":"369692"},{"c":"8404","n":"百和興業-KY","p":"16.60","cg":"-0.0500","v":"368616"},{"c":"5234","n":"達興材料","p":"400.00","cg":"4.0000","v":"365063"},{"c":"2450","n":"神腦","p":"28.90","cg":"-0.2500","v":"364916"},{"c":"3705","n":"永信","p":"57.10","cg":"0.2000","v":"361699"},{"c":"6117","n":"迎廣","p":"77.20","cg":"1.1000","v":"360601"},{"c":"1231","n":"聯華食","p":"86.80","cg":"-0.6000","v":"359188"},{"c":"7750","n":"新代","p":"2290.00","cg":"-80.0000","v":"357029"},{"c":"6937","n":"天虹","p":"287.00","cg":"7.5000","v":"354894"},{"c":"6515","n":"穎崴","p":"9460.00","cg":"10.0000","v":"352535"},{"c":"00640L","n":"富邦日本正2","p":"109.30","cg":"1.6000","v":"352464"},{"c":"3622","n":"洋華","p":"56.50","cg":"0.8000","v":"350097"},{"c":"4571","n":"鈞興-KY","p":"181.50","cg":"0.0000","v":"349168"},{"c":"00703","n":"台新MSCI中國","p":"18.60","cg":"-0.0500","v":"345708"},{"c":"2608","n":"嘉里大榮","p":"28.95","cg":"-0.1500","v":"345178"},{"c":"3150","n":"鈺寶-創","p":"19.95","cg":"1.1500","v":"344682"},{"c":"009810","n":"玉山全球藍籌100","p":"20.35","cg":"-0.0600","v":"344069"},{"c":"00678","n":"群益那斯達克生技","p":"36.49","cg":"-0.0800","v":"343776"},{"c":"2423","n":"固緯","p":"80.20","cg":"2.5000","v":"342602"},{"c":"1806","n":"冠軍","p":"8.21","cg":"-0.0100","v":"339299"},{"c":"9925","n":"新保","p":"40.50","cg":"-0.1500","v":"338448"},{"c":"2424","n":"隴華","p":"11.65","cg":"1.0500","v":"338144"},{"c":"1598","n":"岱宇","p":"19.85","cg":"-0.3500","v":"337875"},{"c":"2438","n":"翔耀","p":"23.40","cg":"0.9000","v":"334200"},{"c":"1702","n":"南僑","p":"31.45","cg":"-0.3500","v":"333681"},{"c":"8442","n":"威宏-KY","p":"41.50","cg":"1.2000","v":"329580"},{"c":"2723","n":"美食-KY","p":"66.10","cg":"-0.8000","v":"328377"},{"c":"00901","n":"永豐智能車供應鏈","p":"49.10","cg":"1.6000","v":"325869"},{"c":"4755","n":"三福化","p":"147.00","cg":"1.5000","v":"325622"},{"c":"1786","n":"科妍","p":"53.00","cg":"-0.5000","v":"323828"},{"c":"00651R","n":"復華香港反1","p":"5.58","cg":"0.0200","v":"323149"},{"c":"2062","n":"橋椿","p":"19.05","cg":"0.0500","v":"322673"},{"c":"2897B","n":"王道銀乙特","p":"11.90","cg":"0.1000","v":"320771"},{"c":"1446","n":"宏和","p":"16.55","cg":"-0.1500","v":"319859"},{"c":"00770","n":"國泰北美科技","p":"68.90","cg":"0.9000","v":"319039"},{"c":"8341","n":"日友","p":"79.30","cg":"-0.3000","v":"318931"},{"c":"1466","n":"聚隆","p":"14.65","cg":"0.3500","v":"317642"},{"c":"3043","n":"科風","p":"23.35","cg":"-0.4500","v":"317158"},{"c":"2415","n":"錩新","p":"30.30","cg":"-0.0500","v":"314268"},{"c":"2477","n":"美隆電","p":"22.05","cg":"0.1500","v":"310201"},{"c":"4560","n":"強信-KY","p":"32.75","cg":"-0.3500","v":"308009"},{"c":"00714","n":"群益道瓊美國地產","p":"21.32","cg":"-0.1200","v":"307988"},{"c":"1340","n":"勝悅-KY","p":"5.66","cg":"-0.0600","v":"307783"},{"c":"2929","n":"淘帝-KY","p":"6.00","cg":"0.0000","v":"307560"},{"c":"00717","n":"富邦美國特別股","p":"15.03","cg":"-0.0400","v":"307196"},{"c":"6782","n":"視陽","p":"197.50","cg":"3.0000","v":"304335"},{"c":"2546","n":"根基","p":"93.40","cg":"-3.0000","v":"303257"},{"c":"4736","n":"泰博","p":"124.00","cg":"-2.0000","v":"302642"},{"c":"2612","n":"中航","p":"54.40","cg":"0.7000","v":"301626"},{"c":"6192","n":"巨路","p":"119.00","cg":"1.5000","v":"299746"},{"c":"1445","n":"大宇","p":"10.70","cg":"-0.3000","v":"297641"},{"c":"2524","n":"京城","p":"36.50","cg":"-2.7500","v":"297557"},{"c":"00903","n":"富邦元宇宙","p":"21.88","cg":"0.4100","v":"296533"},{"c":"6277","n":"宏正","p":"71.50","cg":"-0.9000","v":"296074"},{"c":"6949","n":"沛爾生醫-創","p":"886.00","cg":"-25.0000","v":"295335"},{"c":"3686","n":"達能","p":"17.15","cg":"-0.1000","v":"294868"},{"c":"6491","n":"晶碩","p":"327.00","cg":"-0.5000","v":"292323"},{"c":"5533","n":"皇鼎","p":"13.95","cg":"-0.0500","v":"290811"},{"c":"00762","n":"元大全球AI","p":"123.15","cg":"1.4500","v":"288115"},{"c":"4195","n":"基米-創","p":"15.50","cg":"-0.2000","v":"286932"},{"c":"4155","n":"訊映","p":"15.00","cg":"-0.3000","v":"282850"},{"c":"00647L","n":"元大S&P500正2","p":"133.25","cg":"-0.1000","v":"282420"},{"c":"4588","n":"玖鼎電力","p":"60.50","cg":"1.4000","v":"276144"},{"c":"1587","n":"吉茂","p":"27.90","cg":"-0.1500","v":"275385"},{"c":"1720","n":"生達","p":"62.60","cg":"-0.3000","v":"275182"},{"c":"01010T","n":"京城樂富R1","p":"10.00","cg":"0.0000","v":"274009"},{"c":"6272","n":"驊陞","p":"32.15","cg":"0.0500","v":"273277"},{"c":"6591","n":"動力-KY","p":"55.10","cg":"-0.4000","v":"272456"},{"c":"2616","n":"山隆","p":"13.70","cg":"-0.1500","v":"270625"},{"c":"8462","n":"柏文","p":"136.00","cg":"-3.0000","v":"269503"},{"c":"1417","n":"嘉裕","p":"8.43","cg":"-0.0900","v":"268642"},{"c":"1731","n":"美吾華","p":"21.70","cg":"-0.1000","v":"267476"},{"c":"3416","n":"融程電","p":"177.50","cg":"1.5000","v":"267209"},{"c":"8045","n":"達運光電","p":"62.00","cg":"0.9000","v":"266541"},{"c":"7760","n":"享溫馨","p":"34.00","cg":"0.4000","v":"265938"},{"c":"3308","n":"聯德","p":"22.15","cg":"0.7000","v":"264907"},{"c":"2613","n":"中櫃","p":"21.75","cg":"-0.1500","v":"264443"},{"c":"6890","n":"來億-KY","p":"230.50","cg":"-7.5000","v":"262991"},{"c":"4119","n":"旭富","p":"42.80","cg":"-1.4000","v":"262588"},{"c":"1530","n":"亞崴","p":"29.85","cg":"-0.7000","v":"261849"},{"c":"1725","n":"元禎","p":"41.15","cg":"3.7000","v":"260613"},{"c":"9935","n":"慶豐富","p":"19.30","cg":"0.0000","v":"259513"},{"c":"1474","n":"弘裕","p":"10.15","cg":"-0.1000","v":"257579"},{"c":"1321","n":"大洋","p":"31.15","cg":"-1.0000","v":"256309"},{"c":"5283","n":"禾聯碩","p":"56.20","cg":"1.7000","v":"255998"},{"c":"2482","n":"連宇","p":"17.20","cg":"-0.1500","v":"255433"},{"c":"00634R","n":"富邦上証反1","p":"2.98","cg":"-0.0400","v":"253899"},{"c":"6743","n":"安普新","p":"29.30","cg":"0.3000","v":"252626"},{"c":"5225","n":"東科-KY","p":"73.90","cg":"-0.1000","v":"251765"},{"c":"1713","n":"國化","p":"50.10","cg":"0.1000","v":"250944"},{"c":"2236","n":"百達-KY","p":"137.00","cg":"0.5000","v":"249992"},{"c":"3168","n":"眾福科","p":"45.10","cg":"-2.9000","v":"249385"},{"c":"00737","n":"國泰AI機器人","p":"38.15","cg":"-0.1200","v":"249308"},{"c":"4585","n":"達明","p":"314.00","cg":"0.5000","v":"248837"},{"c":"6689","n":"伊雲谷","p":"67.00","cg":"0.0000","v":"248716"},{"c":"4108","n":"懷特","p":"12.15","cg":"0.1500","v":"248169"},{"c":"5203","n":"訊連","p":"69.00","cg":"0.0000","v":"247776"},{"c":"1451","n":"年興","p":"16.75","cg":"0.0000","v":"247623"},{"c":"7818","n":"溢泰實業","p":"62.10","cg":"-0.1000","v":"247341"},{"c":"7740","n":"熙特爾-創","p":"161.00","cg":"5.0000","v":"245761"},{"c":"3617","n":"碩天","p":"213.00","cg":"1.5000","v":"245406"},{"c":"3057","n":"喬鼎","p":"20.10","cg":"0.4000","v":"244240"},{"c":"00908","n":"富邦入息REITs+","p":"14.80","cg":"-0.0200","v":"242769"},{"c":"6790","n":"永豐實","p":"39.95","cg":"-0.1000","v":"240539"},{"c":"1457","n":"宜進","p":"14.20","cg":"-0.1000","v":"240446"},{"c":"2029","n":"盛餘","p":"20.80","cg":"0.2000","v":"238721"},{"c":"1527","n":"鑽全","p":"33.10","cg":"-0.2000","v":"237973"},{"c":"1473","n":"台南","p":"19.85","cg":"-0.3500","v":"237966"},{"c":"1339","n":"昭輝","p":"43.60","cg":"-0.3500","v":"235790"},{"c":"2364","n":"倫飛","p":"68.40","cg":"0.5000","v":"235345"},{"c":"7730","n":"暉盛-創","p":"187.50","cg":"7.0000","v":"234803"},{"c":"1109","n":"信大","p":"14.50","cg":"-0.1500","v":"234637"},{"c":"1903","n":"士紙","p":"48.05","cg":"-0.0500","v":"234597"},{"c":"2459","n":"敦吉","p":"65.00","cg":"0.6000","v":"234097"},{"c":"9911","n":"櫻花","p":"82.50","cg":"0.0000","v":"232797"},{"c":"00710B","n":"復華彭博非投等債","p":"18.78","cg":"0.0400","v":"230972"},{"c":"2506","n":"太設","p":"8.93","cg":"-0.0300","v":"230417"},{"c":"4569","n":"六方科-KY","p":"187.00","cg":"-3.5000","v":"229691"},{"c":"00666R","n":"富邦恒生國企反1","p":"9.72","cg":"0.0600","v":"229155"},{"c":"00730","n":"富邦臺灣優質高息","p":"29.28","cg":"0.3100","v":"226221"},{"c":"1533","n":"車王電","p":"38.15","cg":"-0.0500","v":"225139"},{"c":"00638R","n":"元大滬深300反1","p":"6.38","cg":"-0.0900","v":"225110"},{"c":"2706","n":"第一店","p":"12.50","cg":"0.0000","v":"224673"},{"c":"6657","n":"華安","p":"36.25","cg":"-0.3500","v":"224493"},{"c":"1623","n":"大東電","p":"218.50","cg":"-1.5000","v":"224328"},{"c":"00943","n":"兆豐電子高息等權","p":"23.37","cg":"0.5600","v":"224248"},{"c":"1535","n":"中宇","p":"50.30","cg":"-0.1000","v":"222926"},{"c":"6598","n":"ABC-KY","p":"23.75","cg":"-0.4000","v":"222572"},{"c":"00982T","n":"平衡兆豐台美動能","p":"16.08","cg":"0.2600","v":"221951"},{"c":"00728","n":"第一金工業30","p":"67.15","cg":"2.8500","v":"220840"},{"c":"4536","n":"拓凱","p":"165.00","cg":"2.0000","v":"220615"},{"c":"5244","n":"弘凱","p":"38.25","cg":"0.5000","v":"218170"},{"c":"6416","n":"瑞祺電通","p":"83.20","cg":"-0.5000","v":"217774"},{"c":"00875","n":"國泰網路資安","p":"46.39","cg":"-0.2100","v":"217675"},{"c":"1419","n":"新紡","p":"66.20","cg":"-0.9000","v":"216926"},{"c":"9908","n":"大台北","p":"29.55","cg":"0.0000","v":"216724"},{"c":"00656R","n":"國泰中國A50反1","p":"5.64","cg":"-0.0700","v":"211400"},{"c":"1617","n":"榮星","p":"15.95","cg":"-0.2500","v":"211090"},{"c":"01007T","n":"兆豐國泰R2","p":"12.61","cg":"0.0000","v":"211000"},{"c":"3716","n":"中化控股","p":"34.65","cg":"-0.0500","v":"208550"},{"c":"4137","n":"麗豐-KY","p":"110.00","cg":"1.0000","v":"204407"},{"c":"6115","n":"鎰勝","p":"48.55","cg":"-0.1000","v":"202581"},{"c":"6933","n":"AMAX-KY","p":"156.50","cg":"-0.5000","v":"202055"},{"c":"2471","n":"資通","p":"53.70","cg":"-0.1000","v":"200597"},{"c":"7821","n":"神數","p":"43.95","cg":"0.0500","v":"200187"},{"c":"00668","n":"國泰美國道瓊","p":"59.30","cg":"-0.3500","v":"200172"},{"c":"02001L","n":"富邦蘋果正二N","p":"195.10","cg":"8.9500","v":"200000"},{"c":"2906","n":"高林","p":"12.95","cg":"0.0500","v":"199771"},{"c":"2849","n":"安泰銀","p":"14.40","cg":"-0.2000","v":"199678"},{"c":"7803","n":"雲象科技-創","p":"22.75","cg":"-0.2500","v":"199448"},{"c":"6625","n":"必應","p":"79.80","cg":"0.6000","v":"196658"},{"c":"6838","n":"台新藥","p":"24.30","cg":"-0.3500","v":"195164"},{"c":"6128","n":"上福","p":"20.60","cg":"-0.4000","v":"193484"},{"c":"5306","n":"桂盟","p":"87.00","cg":"1.3000","v":"192917"},{"c":"7768","n":"頌勝科技","p":"375.00","cg":"2.0000","v":"192847"},{"c":"6283","n":"淳安","p":"24.15","cg":"0.1500","v":"192028"},{"c":"2228","n":"劍麟","p":"88.70","cg":"-0.3000","v":"191496"},{"c":"6916","n":"華凌","p":"22.10","cg":"-0.2000","v":"190628"},{"c":"8499","n":"鼎炫-KY","p":"324.00","cg":"20.0000","v":"189572"},{"c":"6216","n":"居易","p":"23.30","cg":"0.1000","v":"189316"},{"c":"6906","n":"現觀科","p":"90.40","cg":"-1.7000","v":"189021"},{"c":"1438","n":"三地開發","p":"21.15","cg":"-1.1000","v":"186979"},{"c":"1512","n":"瑞利","p":"6.93","cg":"-0.3200","v":"185884"},{"c":"7765","n":"中華資安","p":"233.00","cg":"-5.0000","v":"185639"},{"c":"3447","n":"展達","p":"39.40","cg":"0.0000","v":"185301"},{"c":"2705","n":"六福","p":"16.30","cg":"-0.2000","v":"184529"},{"c":"1906","n":"寶隆","p":"11.35","cg":"-0.1000","v":"184347"},{"c":"00674R","n":"期元大S&P黃金反1","p":"29.36","cg":"0.9400","v":"183090"},{"c":"7786","n":"東方風能","p":"126.50","cg":"-3.5000","v":"182849"},{"c":"1456","n":"怡華","p":"15.60","cg":"0.1000","v":"182751"},{"c":"1760","n":"寶齡富錦","p":"60.20","cg":"0.3000","v":"181891"},{"c":"6645","n":"金萬林-創","p":"16.70","cg":"1.3500","v":"180577"},{"c":"00654R","n":"富邦印度反1","p":"6.72","cg":"-0.0200","v":"180096"},{"c":"020031","n":"統一IC設計臺灣N","p":"11.33","cg":"0.2100","v":"180000"},{"c":"7722","n":"LINEPAY","p":"321.00","cg":"-7.0000","v":"178419"},{"c":"1225","n":"福懋油","p":"31.05","cg":"-1.2000","v":"177781"},{"c":"006206","n":"元大上證50","p":"37.86","cg":"0.4800","v":"176800"},{"c":"6431","n":"光麗-KY","p":"19.00","cg":"-0.3500","v":"176294"},{"c":"2908","n":"特力","p":"20.90","cg":"0.1000","v":"175427"},{"c":"2109","n":"華豐","p":"14.55","cg":"-0.1000","v":"175172"},{"c":"1110","n":"東泥","p":"15.50","cg":"-0.0500","v":"172665"},{"c":"2739","n":"寒舍","p":"36.15","cg":"0.3500","v":"171535"},{"c":"00653L","n":"富邦印度正2","p":"46.78","cg":"0.3400","v":"170532"},{"c":"00972","n":"野村日本動能高息","p":"19.40","cg":"0.0000","v":"170084"},{"c":"1437","n":"勤益控","p":"29.75","cg":"0.2000","v":"167632"},{"c":"00861","n":"元大全球未來通訊","p":"97.50","cg":"1.2500","v":"164442"},{"c":"9930","n":"中聯資源","p":"69.80","cg":"-0.2000","v":"162744"},{"c":"1615","n":"大山","p":"45.15","cg":"-0.0500","v":"162227"},{"c":"3054","n":"立萬利","p":"66.50","cg":"-1.2000","v":"161160"},{"c":"00775B","n":"新光投等債15+","p":"32.40","cg":"0.0000","v":"160000"},{"c":"01009T","n":"王道圓滿R1","p":"5.71","cg":"-0.0100","v":"160000"},{"c":"5215","n":"科嘉-KY","p":"45.35","cg":"0.0000","v":"159409"},{"c":"4552","n":"力達-KY","p":"21.45","cg":"-0.1000","v":"159047"},{"c":"6792","n":"詠業","p":"68.40","cg":"-1.6000","v":"156718"},{"c":"2028","n":"威致","p":"16.75","cg":"0.1500","v":"156393"},{"c":"9924","n":"福興","p":"40.25","cg":"-0.4000","v":"155418"},{"c":"5292","n":"華懋","p":"228.00","cg":"-0.5000","v":"154593"},{"c":"00702","n":"國泰標普低波高息","p":"24.25","cg":"0.0100","v":"153268"},{"c":"2701","n":"萬企","p":"10.60","cg":"0.0500","v":"152339"},{"c":"00783","n":"富邦中証500","p":"30.81","cg":"0.1200","v":"152089"},{"c":"5906","n":"台南-KY","p":"38.25","cg":"-2.6500","v":"150527"},{"c":"9905","n":"大華","p":"21.00","cg":"-0.0500","v":"149713"},{"c":"1452","n":"宏益","p":"10.95","cg":"-0.2000","v":"148608"},{"c":"1539","n":"巨庭","p":"15.80","cg":"0.1000","v":"146104"},{"c":"1737","n":"臺鹽","p":"31.75","cg":"-0.0500","v":"145768"},{"c":"3494","n":"誠研","p":"8.02","cg":"-0.0300","v":"143611"},{"c":"6957","n":"裕慶-KY","p":"190.00","cg":"0.5000","v":"143191"},{"c":"2514","n":"龍邦","p":"13.60","cg":"-0.1000","v":"142256"},{"c":"2642","n":"宅配通","p":"21.10","cg":"0.0500","v":"142052"},{"c":"6671","n":"三能-KY","p":"25.00","cg":"-0.7500","v":"141552"},{"c":"4106","n":"雃博","p":"23.30","cg":"-0.1000","v":"141450"},{"c":"2887E","n":"台新新光戊特一","p":"50.70","cg":"0.0000","v":"141170"},{"c":"1410","n":"南染","p":"24.70","cg":"-0.1500","v":"141070"},{"c":"4771","n":"望隼","p":"192.50","cg":"1.0000","v":"138753"},{"c":"4438","n":"廣越","p":"59.80","cg":"-1.3000","v":"137284"},{"c":"1465","n":"偉全","p":"12.40","cg":"-0.1000","v":"136965"},{"c":"6281","n":"全國電","p":"51.40","cg":"-0.1000","v":"135484"},{"c":"8478","n":"東哥遊艇","p":"151.50","cg":"0.5000","v":"135347"},{"c":"6969","n":"成信實業*-創","p":"25.70","cg":"-0.7000","v":"132584"},{"c":"9942","n":"茂順","p":"118.50","cg":"0.0000","v":"132202"},{"c":"1783","n":"和康生","p":"38.55","cg":"-0.2000","v":"132195"},{"c":"4583","n":"台灣精銳","p":"630.00","cg":"0.0000","v":"131625"},{"c":"6863","n":"永道-KY","p":"95.40","cg":"-1.3000","v":"131220"},{"c":"5288","n":"豐祥-KY","p":"187.50","cg":"-1.5000","v":"130512"},{"c":"1213","n":"大飲","p":"8.00","cg":"-0.3300","v":"129125"},{"c":"1423","n":"利華","p":"38.65","cg":"-1.0000","v":"128692"},{"c":"1526","n":"日馳","p":"14.60","cg":"0.0500","v":"127244"},{"c":"9931","n":"欣高","p":"35.10","cg":"-0.1500","v":"125393"},{"c":"1234","n":"黑松","p":"34.95","cg":"0.1000","v":"123440"},{"c":"2432","n":"倚天酷碁-創","p":"28.50","cg":"0.0000","v":"123000"},{"c":"6923","n":"中台","p":"78.00","cg":"0.3000","v":"122932"},{"c":"4935","n":"茂林-KY","p":"39.65","cg":"-0.4000","v":"122041"},{"c":"00711B","n":"復華彭博新興債","p":"16.09","cg":"0.0100","v":"121872"},{"c":"4930","n":"燦星網","p":"17.45","cg":"0.1000","v":"121866"},{"c":"4441","n":"振大環球","p":"199.00","cg":"-1.0000","v":"119715"},{"c":"1733","n":"五鼎","p":"29.40","cg":"0.1000","v":"119370"},{"c":"2887H","n":"台新新光庚特二","p":"41.25","cg":"0.1000","v":"116037"},{"c":"1441","n":"大東","p":"9.12","cg":"-0.1300","v":"115418"},{"c":"2247","n":"汎德永業","p":"234.50","cg":"-3.5000","v":"115347"},{"c":"00689R","n":"國泰20年美債反1","p":"21.74","cg":"0.1000","v":"114000"},{"c":"01002T","n":"土銀國泰R1","p":"13.99","cg":"-0.0100","v":"113000"},{"c":"6606","n":"建德工業","p":"24.90","cg":"-0.1000","v":"112885"},{"c":"00739","n":"元大MSCI A股","p":"29.86","cg":"0.3100","v":"111861"},{"c":"2707","n":"晶華","p":"178.50","cg":"-0.5000","v":"111544"},{"c":"911622","n":"泰聚亨-DR","p":"3.85","cg":"0.0900","v":"111390"},{"c":"2748","n":"雲品","p":"40.25","cg":"-0.1500","v":"110503"},{"c":"8411","n":"福貞-KY","p":"12.10","cg":"-0.0500","v":"110193"},{"c":"7631","n":"聚賢研發-創","p":"139.00","cg":"7.5000","v":"110187"},{"c":"9902","n":"台火","p":"13.75","cg":"0.0500","v":"109934"},{"c":"6614","n":"資拓宏宇","p":"40.15","cg":"-0.7500","v":"109804"},{"c":"1414","n":"東和","p":"17.55","cg":"0.0500","v":"109378"},{"c":"00683L","n":"期元大美元指正2","p":"21.95","cg":"0.3200","v":"108000"},{"c":"1805","n":"寶徠","p":"10.35","cg":"0.0000","v":"107622"},{"c":"2704","n":"國賓","p":"46.10","cg":"0.5000","v":"107613"},{"c":"2488","n":"漢平","p":"54.80","cg":"0.0000","v":"107376"},{"c":"4133","n":"亞諾法","p":"20.70","cg":"0.0000","v":"107180"},{"c":"9943","n":"好樂迪","p":"57.40","cg":"-0.2000","v":"106716"},{"c":"6965","n":"中傑-KY","p":"77.80","cg":"0.0000","v":"106480"},{"c":"8463","n":"潤泰材","p":"21.45","cg":"0.1500","v":"106475"},{"c":"2430","n":"燦坤","p":"18.45","cg":"0.0000","v":"106368"},{"c":"8201","n":"無敵","p":"13.50","cg":"0.0000","v":"106325"},{"c":"1338","n":"廣華-KY","p":"17.20","cg":"0.0000","v":"106317"},{"c":"00736","n":"國泰新興市場","p":"31.60","cg":"0.3000","v":"106113"},{"c":"3557","n":"嘉威","p":"26.20","cg":"-0.4500","v":"105791"},{"c":"4999","n":"鑫禾","p":"20.55","cg":"-0.1000","v":"102666"},{"c":"6582","n":"申豐","p":"32.00","cg":"0.5500","v":"100088"},{"c":"2013","n":"中鋼構","p":"42.95","cg":"0.0500","v":"98568"},{"c":"7791","n":"皇家可口","p":"62.20","cg":"-0.4000","v":"98399"},{"c":"00709","n":"富邦歐洲","p":"39.00","cg":"-0.3200","v":"97533"},{"c":"0051","n":"元大中型100","p":"151.50","cg":"3.8000","v":"94689"},{"c":"1732","n":"毛寶","p":"26.30","cg":"0.0000","v":"94583"},{"c":"1220","n":"台榮","p":"11.70","cg":"0.0000","v":"94424"},{"c":"3164","n":"景岳","p":"16.30","cg":"-0.1000","v":"92332"},{"c":"6958","n":"日盛台駿","p":"17.15","cg":"-0.0500","v":"92255"},{"c":"2762","n":"世界健身-KY","p":"84.50","cg":"-0.8000","v":"92053"},{"c":"4148","n":"全宇生技-KY","p":"30.65","cg":"-0.2000","v":"91007"},{"c":"2433","n":"互盛電","p":"44.35","cg":"-0.1500","v":"90713"},{"c":"6201","n":"亞弘電","p":"48.30","cg":"-0.1000","v":"90351"},{"c":"3669","n":"圓展","p":"35.85","cg":"0.4000","v":"90288"},{"c":"6934","n":"心誠鎂","p":"68.70","cg":"-2.6000","v":"90019"},{"c":"4942","n":"嘉彰","p":"37.55","cg":"-0.2500","v":"89418"},{"c":"4557","n":"永新-KY","p":"50.90","cg":"1.2000","v":"89402"},{"c":"6931","n":"青松健康","p":"40.30","cg":"-0.5000","v":"89343"},{"c":"1752","n":"南光","p":"32.70","cg":"-0.1000","v":"89180"},{"c":"6184","n":"大豐電","p":"46.80","cg":"-0.1500","v":"87792"},{"c":"1558","n":"伸興","p":"91.20","cg":"-0.3000","v":"87667"},{"c":"7705","n":"三商餐飲","p":"32.00","cg":"0.1500","v":"87132"},{"c":"2722","n":"夏都","p":"23.05","cg":"-0.2500","v":"87085"},{"c":"1472","n":"三洋實業","p":"88.60","cg":"-2.4000","v":"87042"},{"c":"1730","n":"花仙子","p":"53.30","cg":"0.3000","v":"85805"},{"c":"01001T","n":"土銀富邦R1","p":"11.63","cg":"0.0000","v":"84005"},{"c":"2114","n":"鑫永銓","p":"89.30","cg":"0.3000","v":"82707"},{"c":"3018","n":"隆銘綠能","p":"12.00","cg":"0.1000","v":"82498"},{"c":"1453","n":"大將","p":"11.65","cg":"-0.1500","v":"82140"},{"c":"1531","n":"高林股","p":"12.90","cg":"0.0000","v":"81874"},{"c":"2115","n":"六暉-KY","p":"20.50","cg":"-0.1000","v":"80684"},{"c":"6951","n":"青新-創","p":"77.60","cg":"-1.2000","v":"80055"},{"c":"9927","n":"泰銘","p":"69.80","cg":"0.4000","v":"79150"},{"c":"00771","n":"元大US高息特別股","p":"15.75","cg":"-0.0400","v":"77742"},{"c":"3679","n":"新至陞","p":"110.50","cg":"-0.5000","v":"76933"},{"c":"9929","n":"秋雨","p":"12.00","cg":"-0.7000","v":"76434"},{"c":"6666","n":"羅麗芬-KY","p":"43.25","cg":"0.3000","v":"76336"},{"c":"6722","n":"輝創","p":"37.35","cg":"-0.0500","v":"75090"},{"c":"6936","n":"永鴻生技","p":"33.00","cg":"-0.4000","v":"74277"},{"c":"1324","n":"地球","p":"10.45","cg":"0.0500","v":"73854"},{"c":"2348A","n":"海悅甲特","p":"37.50","cg":"-0.0500","v":"73188"},{"c":"2881B","n":"富邦金乙特","p":"62.60","cg":"0.0000","v":"72622"},{"c":"2702","n":"華園","p":"12.90","cg":"-0.1000","v":"72608"},{"c":"00657","n":"國泰日經225","p":"84.40","cg":"1.5000","v":"71749"},{"c":"6796","n":"晉弘","p":"59.00","cg":"-0.3000","v":"71038"},{"c":"8940","n":"新天地","p":"16.70","cg":"-0.3000","v":"70232"},{"c":"9944","n":"新麗","p":"17.70","cg":"-0.0500","v":"70174"},{"c":"020034","n":"元大IC設計N","p":"15.85","cg":"0.6100","v":"68000"},{"c":"2881A","n":"富邦特","p":"63.80","cg":"-0.1000","v":"67136"},{"c":"1537","n":"廣隆","p":"127.00","cg":"-0.5000","v":"66365"},{"c":"00660","n":"元大歐洲50","p":"45.67","cg":"0.1600","v":"66195"},{"c":"1236","n":"宏亞","p":"25.85","cg":"0.0500","v":"66181"},{"c":"8367","n":"建新國際","p":"40.55","cg":"0.2500","v":"65450"},{"c":"6921","n":"嘉雨思-創","p":"70.20","cg":"-1.3000","v":"65437"},{"c":"3432","n":"台端","p":"18.95","cg":"0.2500","v":"65185"},{"c":"6230","n":"尼得科超眾","p":"135.00","cg":"2.5000","v":"65108"},{"c":"4943","n":"康控-KY","p":"8.66","cg":"-0.4000","v":"64718"},{"c":"4190","n":"佐登-KY","p":"24.50","cg":"-0.3000","v":"63452"},{"c":"911608","n":"明輝-DR","p":"2.91","cg":"-0.0200","v":"63000"},{"c":"4440","n":"宜新實業","p":"17.15","cg":"0.0500","v":"62765"},{"c":"2881C","n":"富邦金丙特","p":"51.30","cg":"-0.1000","v":"61586"},{"c":"00661","n":"元大日經225","p":"93.55","cg":"1.6000","v":"61398"},{"c":"01004T","n":"土銀富邦R2","p":"10.44","cg":"0.0000","v":"61008"},{"c":"7736","n":"虎山","p":"71.60","cg":"-1.1000","v":"60489"},{"c":"6504","n":"南六","p":"36.30","cg":"0.1000","v":"60462"},{"c":"2239","n":"英利-KY","p":"22.70","cg":"0.0000","v":"60383"},{"c":"2250","n":"IKKA-KY","p":"61.30","cg":"-0.4000","v":"60272"},{"c":"2891C","n":"中信金丙特","p":"62.70","cg":"0.0000","v":"59961"},{"c":"1463","n":"強盛新","p":"17.45","cg":"-0.1500","v":"58730"},{"c":"5546","n":"永固-KY","p":"16.30","cg":"-0.7500","v":"58188"},{"c":"1614","n":"三洋電","p":"31.80","cg":"-0.1000","v":"57540"},{"c":"2923","n":"鼎固-KY","p":"24.00","cg":"0.4500","v":"57232"},{"c":"6914","n":"阜爾運通","p":"143.50","cg":"1.0000","v":"54928"},{"c":"6183","n":"關貿","p":"90.00","cg":"-0.4000","v":"54491"},{"c":"6952","n":"大武山","p":"36.00","cg":"-0.0500","v":"54274"},{"c":"2887G","n":"台新新光庚特一","p":"43.15","cg":"0.0000","v":"52820"},{"c":"6794","n":"向榮生技","p":"79.20","cg":"-0.2000","v":"52131"},{"c":"1470","n":"大統新創","p":"22.40","cg":"0.0000","v":"52004"},{"c":"910861","n":"神州-DR","p":"4.49","cg":"-0.0100","v":"51069"},{"c":"1583","n":"程泰","p":"50.90","cg":"0.6000","v":"50623"},{"c":"1341","n":"富林-KY","p":"61.90","cg":"-0.1000","v":"50048"},{"c":"1521","n":"大億","p":"26.55","cg":"-0.0500","v":"49442"},{"c":"4737","n":"華廣","p":"57.50","cg":"0.6000","v":"48999"},{"c":"2227","n":"裕日車","p":"49.25","cg":"-0.0500","v":"48740"},{"c":"8487","n":"愛爾達-創","p":"79.00","cg":"0.4000","v":"48189"},{"c":"2901","n":"欣欣","p":"23.80","cg":"-0.0500","v":"47262"},{"c":"2882B","n":"國泰金乙特","p":"60.80","cg":"0.0000","v":"46966"},{"c":"3266","n":"昇陽","p":"13.50","cg":"-0.2000","v":"46935"},{"c":"4572","n":"駐龍","p":"144.00","cg":"-0.5000","v":"46510"},{"c":"8443","n":"阿瘦","p":"11.40","cg":"0.0000","v":"46430"},{"c":"9928","n":"中視","p":"18.60","cg":"0.0000","v":"46310"},{"c":"1468","n":"昶和","p":"11.95","cg":"-0.0500","v":"46000"},{"c":"3130","n":"一零四","p":"223.50","cg":"-0.5000","v":"45346"},{"c":"1817","n":"凱撒衛","p":"40.45","cg":"-0.1500","v":"44641"},{"c":"1101B","n":"台泥乙特","p":"45.30","cg":"0.0500","v":"41317"},{"c":"1439","n":"雋揚","p":"24.30","cg":"-1.0000","v":"41107"},{"c":"6534","n":"正瀚-創","p":"92.00","cg":"-1.0000","v":"40051"},{"c":"6835","n":"圓裕","p":"36.80","cg":"0.2500","v":"40043"},{"c":"0053","n":"元大電子","p":"252.15","cg":"7.2000","v":"39885"},{"c":"6988","n":"威力暘-創","p":"13.95","cg":"-0.0500","v":"39378"},{"c":"6674","n":"鋐寶科技","p":"17.40","cg":"-0.0500","v":"39020"},{"c":"020020","n":"元大台股領航N","p":"29.40","cg":"0.6000","v":"39000"},{"c":"9941A","n":"裕融甲特","p":"50.60","cg":"0.1000","v":"38789"},{"c":"6924","n":"榮惠-KY創","p":"126.50","cg":"1.5000","v":"38554"},{"c":"6641","n":"基士德-KY","p":"18.45","cg":"0.1000","v":"38517"},{"c":"9110","n":"越南控-DR","p":"3.20","cg":"-0.2000","v":"37901"},{"c":"2904","n":"匯僑","p":"14.20","cg":"0.0500","v":"37466"},{"c":"1315","n":"達新","p":"62.20","cg":"-0.1000","v":"35854"},{"c":"1475","n":"業旺","p":"26.95","cg":"-0.4500","v":"35208"},{"c":"1256","n":"鮮活果汁-KY","p":"181.00","cg":"-0.5000","v":"35052"},{"c":"2838A","n":"聯邦銀甲特","p":"54.30","cg":"0.0000","v":"33000"},{"c":"6918","n":"愛派司","p":"74.00","cg":"0.1000","v":"32860"},{"c":"1418","n":"東華","p":"18.00","cg":"-0.5000","v":"32509"},{"c":"2887F","n":"台新新光戊特二","p":"47.15","cg":"0.0500","v":"32448"},{"c":"9918","n":"欣天然","p":"43.05","cg":"-0.0500","v":"32185"},{"c":"5007","n":"三星","p":"56.20","cg":"0.2000","v":"31396"},{"c":"2248","n":"華勝-KY","p":"55.80","cg":"-0.5000","v":"31045"},{"c":"0057","n":"富邦摩台","p":"324.95","cg":"7.7500","v":"30504"},{"c":"3593","n":"力銘","p":"16.00","cg":"-0.0500","v":"30439"},{"c":"2887Z1","n":"台新新光己特","p":"18.05","cg":"0.0000","v":"30332"},{"c":"1726","n":"永記","p":"78.10","cg":"-0.3000","v":"29777"},{"c":"6955","n":"邦睿生技-創","p":"128.00","cg":"-4.5000","v":"29629"},{"c":"2024","n":"志聯","p":"14.20","cg":"0.1000","v":"29097"},{"c":"2373","n":"震旦行","p":"58.10","cg":"0.1000","v":"27289"},{"c":"6754","n":"匯僑設計","p":"45.20","cg":"-0.3000","v":"27278"},{"c":"1541","n":"錩泰","p":"22.10","cg":"0.1000","v":"27267"},{"c":"6225","n":"天瀚","p":"21.60","cg":"-2.4000","v":"26485"},{"c":"9912","n":"偉聯","p":"12.55","cg":"-0.1000","v":"25303"},{"c":"8466","n":"美吉吉-KY","p":"15.60","cg":"0.0500","v":"25250"},{"c":"2836A","n":"高雄銀甲特","p":"24.60","cg":"-0.0500","v":"25000"},{"c":"9937","n":"全國","p":"55.30","cg":"-0.2000","v":"23776"},{"c":"2002A","n":"中鋼特","p":"38.30","cg":"0.0000","v":"23238"},{"c":"7732","n":"金興精密","p":"36.00","cg":"0.0000","v":"23108"},{"c":"2008","n":"高興昌","p":"30.80","cg":"0.0000","v":"22827"},{"c":"8481","n":"政伸","p":"42.05","cg":"-0.0500","v":"22751"},{"c":"1233","n":"天仁","p":"27.95","cg":"-0.0500","v":"22276"},{"c":"1413","n":"宏洲","p":"9.38","cg":"-0.0600","v":"22253"},{"c":"2254","n":"巨鎧精密-創","p":"59.00","cg":"-3.2000","v":"22215"},{"c":"6887","n":"寶綠特-KY","p":"35.00","cg":"0.8000","v":"22013"},{"c":"1454","n":"台富","p":"12.95","cg":"0.1000","v":"22012"},{"c":"4994","n":"傳奇","p":"91.00","cg":"-0.8000","v":"21726"},{"c":"2945","n":"三商家購","p":"42.50","cg":"-0.4000","v":"21706"},{"c":"1235","n":"興泰","p":"36.75","cg":"-0.9000","v":"21371"},{"c":"8488","n":"吉源-KY","p":"10.30","cg":"-0.2500","v":"21054"},{"c":"2712","n":"遠雄來","p":"15.20","cg":"0.0000","v":"21051"},{"c":"4581","n":"光隆精密-KY","p":"50.00","cg":"0.0500","v":"20076"},{"c":"6771","n":"平和環保-創","p":"42.00","cg":"0.0000","v":"19567"},{"c":"00851","n":"台新全球AI","p":"74.20","cg":"0.9000","v":"19073"},{"c":"9926","n":"新海","p":"49.80","cg":"0.6000","v":"18254"},{"c":"7823","n":"奧義賽博-KY創","p":"81.50","cg":"-0.6000","v":"18204"},{"c":"2939","n":"永邑-KY","p":"21.35","cg":"-0.5500","v":"18000"},{"c":"8112A","n":"至上甲特","p":"46.80","cg":"0.0000","v":"16869"},{"c":"4439","n":"冠星-KY","p":"91.80","cg":"0.2000","v":"16184"},{"c":"006204","n":"永豐臺灣加權","p":"239.30","cg":"7.5000","v":"16002"},{"c":"020039","n":"元大加權N","p":"15.22","cg":"0.4900","v":"16000"},{"c":"1516","n":"川飛","p":"20.40","cg":"-0.1000","v":"15716"},{"c":"00682U","n":"期元大美元指數","p":"20.58","cg":"0.0400","v":"15449"},{"c":"6464","n":"台數科","p":"78.00","cg":"0.0000","v":"15419"},{"c":"6908","n":"宏碁遊戲-創","p":"39.00","cg":"0.2500","v":"14879"},{"c":"1443","n":"立益物流","p":"27.45","cg":"-0.4500","v":"14566"},{"c":"020029","n":"元大ESG高股息N","p":"19.13","cg":"0.6300","v":"14000"},{"c":"020030","n":"統一智慧電動車N","p":"19.64","cg":"0.5400","v":"14000"},{"c":"6592B","n":"和潤企業乙特","p":"97.60","cg":"0.1000","v":"13388"},{"c":"1538","n":"正峰","p":"11.40","cg":"0.0000","v":"12867"},{"c":"1203","n":"味王","p":"42.80","cg":"-0.2000","v":"12055"},{"c":"1525","n":"江申","p":"66.00","cg":"0.0000","v":"12013"},{"c":"910322","n":"康師傅-DR","p":"21.15","cg":"-0.1000","v":"11645"},{"c":"00684R","n":"期元大美元指反1","p":"14.95","cg":"0.0000","v":"11300"},{"c":"5871A","n":"中租-KY甲特","p":"103.00","cg":"0.5000","v":"10418"},{"c":"020037","n":"元大金融高股息N","p":"11.04","cg":"-0.2100","v":"10000"},{"c":"020038","n":"元大ESG配息N","p":"14.75","cg":"0.3700","v":"10000"},{"c":"8101","n":"華冠","p":"13.75","cg":"-0.7000","v":"9265"},{"c":"00681R","n":"元大美債20反1","p":"20.82","cg":"0.0600","v":"9138"},{"c":"8482","n":"商億-KY","p":"48.35","cg":"0.0000","v":"9020"},{"c":"1312A","n":"國喬特","p":"21.75","cg":"0.0000","v":"9009"},{"c":"2496","n":"卓越","p":"65.10","cg":"0.1000","v":"8897"},{"c":"8467","n":"波力-KY","p":"126.00","cg":"0.5000","v":"8285"},{"c":"6958A","n":"日盛台駿甲特","p":"18.30","cg":"0.0000","v":"8100"},{"c":"020000","n":"富邦特選蘋果N","p":"35.95","cg":"0.8900","v":"7000"},{"c":"020028","n":"元大特選電動車N","p":"20.82","cg":"0.1700","v":"7000"},{"c":"020036","n":"元大金融配息N","p":"9.90","cg":"-0.1900","v":"7000"},{"c":"2891B","n":"中信金乙特","p":"64.30","cg":"0.0000","v":"6810"},{"c":"006203","n":"元大MSCI台灣","p":"201.75","cg":"7.7500","v":"6750"},{"c":"2321","n":"東訊","p":"13.90","cg":"-0.1500","v":"6289"},{"c":"6807","n":"峰源-KY","p":"33.40","cg":"-0.2500","v":"6280"},{"c":"00707R","n":"期元大S&P日圓反1","p":"32.46","cg":"0.1900","v":"5000"},{"c":"6592A","n":"和潤企業甲特","p":"97.90","cg":"-0.1000","v":"4800"},{"c":"020012","n":"富邦行動通訊N","p":"25.24","cg":"0.3800","v":"4000"},{"c":"020032","n":"元大綠能N","p":"10.96","cg":"0.0000","v":"4000"},{"c":"1435","n":"中福","p":"15.50","cg":"1.4000","v":"3596"},{"c":"6581","n":"鋼聯","p":"109.00","cg":"0.0000","v":"3505"},{"c":"2910","n":"統領","p":"22.70","cg":"-0.4000","v":"3018"},{"c":"00636K","n":"國泰中國A50+U","p":"9.19","cg":"0.0100","v":"500"},{"c":"1522A","n":"堤維西甲特","p":"","cg":"0.0000","v":"425"},{"c":"00657K","n":"國泰日經225+U","p":"26.71","cg":"0.3000","v":"200"},{"c":"00668K","n":"國泰美國道瓊+U","p":"18.86","cg":"0.0300","v":"200"},{"c":"6655","n":"科定","p":"","cg":"0.0000","v":"22"}]